[{"position_word": [{"word": "Au", "type_entity": "", "lemma": "Au", "pos_tag": "DET", "position": 1, "title": false}, {"word": "terme", "type_entity": "", "lemma": "terme", "pos_tag": "NOUN", "position": 2, "title": false}, {"word": "intense", "type_entity": "", "lemma": "intense", "pos_tag": "NOUN", "position": 5, "title": false}, {"word": "bataille", "type_entity": "", "lemma": "batailler", "pos_tag": "NOUN", "position": 6, "title": false}, {"word": "juridique", "type_entity": "", "lemma": "juridique", "pos_tag": "ADJ", "position": 7, "title": false}, {"word": "46", "type_entity": "", "lemma": "46", "pos_tag": "NUM", "position": 8, "title": false}, {"word": "appartements", "type_entity": "", "lemma": "appartement", "pos_tag": "NOUN", "position": 9, "title": false}, {"word": "situes", "type_entity": "", "lemma": "situer", "pos_tag": "ADJ", "position": 10, "title": false}, {"word": "16e", "type_entity": "", "lemma": "16e", "pos_tag": "ADJ", "position": 13, "title": false}, {"word": "arrondissement", "type_entity": "", "lemma": "arrondissement", "pos_tag": "NOUN", "position": 14, "title": false}, {"word": "capitale", "type_entity": "", "lemma": "capital", "pos_tag": "NOUN", "position": 17, "title": false}, {"word": "vont", "type_entity": "", "lemma": "aller", "pos_tag": "VERB", "position": 18, "title": false}, {"word": "etre", "type_entity": "", "lemma": "etre", "pos_tag": "AUX", "position": 19, "title": false}, {"word": "transformes", "type_entity": "", "lemma": "transformer", "pos_tag": "AUX", "position": 20, "title": false}, {"word": "HLM.Et", "type_entity": "", "lemma": "HLM.Et", "pos_tag": "PROPN", "position": 22, "title": false}, {"word": "finalement", "type_entity": "", "lemma": "finalement", "pos_tag": "ADV", "position": 24, "title": false}, {"word": "passait", "type_entity": "", "lemma": "passer", "pos_tag": "VERB", "position": 27, "title": false}, {"word": "visitant", "type_entity": "", "lemma": "visiter", "pos_tag": "VERB", "position": 31, "title": false}, {"word": "hier", "type_entity": "", "lemma": "hier", "pos_tag": "ADV", "position": 32, "title": false}, {"word": "certains", "type_entity": "", "lemma": "certain", "pos_tag": "PRON", "position": 33, "title": false}, {"word": "46", "type_entity": "", "lemma": "46", "pos_tag": "NUM", "position": 35, "title": false}, {"word": "appartements", "type_entity": "", "lemma": "appartement", "pos_tag": "NOUN", "position": 36, "title": false}, {"word": "situes", "type_entity": "", "lemma": "situer", "pos_tag": "ADJ", "position": 37, "title": false}, {"word": "tres", "type_entity": "", "lemma": "tres", "pos_tag": "ADJ", "position": 40, "title": false}, {"word": "chic", "type_entity": "", "lemma": "chic", "pos_tag": "NOUN", "position": 41, "title": true}, {"word": "16e", "type_entity": "", "lemma": "16e", "pos_tag": "ADJ", "position": 42, "title": false}, {"word": "arrondissement", "type_entity": "", "lemma": "arrondissement", "pos_tag": "NOUN", "position": 43, "title": false}, {"word": "Paris", "type_entity": "LOC", "lemma": "Paris", "pos_tag": "PROPN", "position": 45, "title": false}, {"word": "vendus", "type_entity": "", "lemma": "vendu", "pos_tag": "VERB", "position": 46, "title": false}, {"word": "ville", "type_entity": "", "lemma": "ville", "pos_tag": "NOUN", "position": 49, "title": false}, {"word": "bailleur", "type_entity": "", "lemma": "bailleur", "pos_tag": "NOUN", "position": 51, "title": false}, {"word": "ElogieSiemp", "type_entity": "ORG", "lemma": "ElogieSiemp", "pos_tag": "ADJ", "position": 52, "title": false}, {"word": "faire", "type_entity": "", "lemma": "faire", "pos_tag": "VERB", "position": 55, "title": false}, {"word": "logements", "type_entity": "", "lemma": "logement", "pos_tag": "NOUN", "position": 57, "title": false}, {"word": "sociaux", "type_entity": "", "lemma": "social", "pos_tag": "ADJ", "position": 58, "title": false}, {"word": "Ian_Brossat", "type_entity": "PER", "lemma": "Ian_Brossat", "pos_tag": "ADJ", "position": 59, "title": false}, {"word": "adjoint", "type_entity": "", "lemma": "adjoindre", "pos_tag": "NOUN", "position": 60, "title": false}, {"word": "PCF", "type_entity": "ORG", "lemma": "PCF", "pos_tag": "PROPN", "position": 61, "title": false}, {"word": "charge", "type_entity": "", "lemma": "charger", "pos_tag": "NOUN", "position": 63, "title": false}, {"word": "logement", "type_entity": "", "lemma": "logement", "pos_tag": "ADV", "position": 65, "title": true}, {"word": "montre", "type_entity": "", "lemma": "montrer", "pos_tag": "ADJ", "position": 68, "title": false}, {"word": "optimiste", "type_entity": "", "lemma": "optimiste", "pos_tag": "ADJ", "position": 69, "title": false}, {"word": "Nous", "type_entity": "", "lemma": "Nous", "pos_tag": "PRON", "position": 71, "title": false}, {"word": "faisons", "type_entity": "", "lemma": "faire", "pos_tag": "VERB", "position": 72, "title": false}, {"word": "souvent", "type_entity": "", "lemma": "souvent", "pos_tag": "ADV", "position": 73, "title": false}, {"word": "experience", "type_entity": "", "lemma": "experience", "pos_tag": "NOUN", "position": 75, "title": false}, {"word": "Habitat", "type_entity": "LOC", "lemma": "Habitat", "pos_tag": "NOUN", "position": 1, "title": false}, {"word": "Paris", "type_entity": "LOC", "lemma": "Paris", "pos_tag": "PROPN", "position": 4, "title": false}, {"word": "logement", "type_entity": "", "lemma": "logement", "pos_tag": "ADV", "position": 5, "title": true}, {"word": "social", "type_entity": "", "lemma": "social", "pos_tag": "ADJ", "position": 6, "title": true}, {"word": "quartier", "type_entity": "", "lemma": "quartier", "pos_tag": "DET", "position": 8, "title": true}, {"word": "chic", "type_entity": "", "lemma": "chic", "pos_tag": "NOUN", "position": 9, "title": true}], "id_art": "65d16ff6161167430d9c2ee2d369e862", "article": {"surname_author": [], "name_newspaper": "Humanite", "date_publication": "2018-01-17"}}]