[{"position_word": [{"word": "Ce", "type_entity": "", "lemma": "Ce", "pos_tag": "PRON", "position": 1, "title": false}, {"word": "revelations", "type_entity": "", "lemma": "revelations", "pos_tag": "NOUN", "position": 6, "title": false}, {"word": "edition", "type_entity": "", "lemma": "edition", "pos_tag": "NOUN", "position": 9, "title": false}, {"word": "2017", "type_entity": "", "lemma": "2017", "pos_tag": "NUM", "position": 10, "title": false}, {"word": "Festival_du_court_metrage", "type_entity": "MISC", "lemma": "Festival_du_court_metrage", "pos_tag": "NOUN", "position": 12, "title": false}, {"word": "ClermontFerrand", "type_entity": "ORG", "lemma": "ClermontFerrand", "pos_tag": "PROPN", "position": 14, "title": false}, {"word": "ete", "type_entity": "", "lemma": "ete", "pos_tag": "AUX", "position": 18, "title": false}, {"word": "prime", "type_entity": "", "lemma": "primer", "pos_tag": "NOUN", "position": 19, "title": false}, {"word": "Les_Miserables_de_Ladj_Ly", "type_entity": "", "lemma": "Les_Miserables_de_Ladj_Ly", "pos_tag": "ADJ", "position": 20, "title": false}, {"word": "ardent", "type_entity": "", "lemma": "ardent", "pos_tag": "ADV", "position": 21, "title": false}, {"word": "militant", "type_entity": "", "lemma": "militer", "pos_tag": "VERB", "position": 22, "title": false}, {"word": "collectif", "type_entity": "", "lemma": "collectif", "pos_tag": "NOUN", "position": 24, "title": false}, {"word": "Kourtrajme", "type_entity": "LOC", "lemma": "Kourtrajme", "pos_tag": "PROPN", "position": 25, "title": false}, {"word": "voir", "type_entity": "", "lemma": "voir", "pos_tag": "VERB", "position": 28, "title": false}, {"word": "Telerama.fr", "type_entity": "LOC", "lemma": "Telerama.fr", "pos_tag": "NOUN", "position": 30, "title": false}, {"word": "jusqu", "type_entity": "", "lemma": "jusqu", "pos_tag": "VERB", "position": 31, "title": false}, {"word": "31janvier", "type_entity": "", "lemma": "31janvier", "pos_tag": "NUM", "position": 33, "title": false}, {"word": "Originaire", "type_entity": "", "lemma": "Originaire", "pos_tag": "ADJ", "position": 35, "title": false}, {"word": "cite", "type_entity": "", "lemma": "citer", "pos_tag": "NOUN", "position": 38, "title": false}, {"word": "Bosquets", "type_entity": "LOC", "lemma": "Bosquets", "pos_tag": "NOUN", "position": 40, "title": false}, {"word": "ClichyMontfermeil", "type_entity": "LOC", "lemma": "ClichyMontfermeil", "pos_tag": "PROPN", "position": 42, "title": false}, {"word": "Ladj_Ly", "type_entity": "LOC", "lemma": "Ladj_Ly", "pos_tag": "PROPN", "position": 43, "title": false}, {"word": "militant", "type_entity": "", "lemma": "militer", "pos_tag": "VERB", "position": 47, "title": false}, {"word": "collectif", "type_entity": "", "lemma": "collectif", "pos_tag": "NOUN", "position": 49, "title": false}, {"word": "Kourtrajme", "type_entity": "LOC", "lemma": "Kourtrajme", "pos_tag": "PROPN", "position": 50, "title": false}, {"word": "signe", "type_entity": "", "lemma": "signer", "pos_tag": "VERB", "position": 54, "title": false}, {"word": "documentaire", "type_entity": "", "lemma": "documentaire", "pos_tag": "ADJ", "position": 56, "title": false}, {"word": "emeutes", "type_entity": "", "lemma": "emeutes", "pos_tag": "NOUN", "position": 59, "title": false}, {"word": "2005", "type_entity": "", "lemma": "2005", "pos_tag": "NUM", "position": 61, "title": false}, {"word": "banlieues", "type_entity": "", "lemma": "banlieue", "pos_tag": "NOUN", "position": 64, "title": false}, {"word": "365", "type_entity": "", "lemma": "365", "pos_tag": "NUM", "position": 65, "title": false}, {"word": "jours", "type_entity": "", "lemma": "jour", "pos_tag": "NOUN", "position": 66, "title": false}, {"word": "ClichyMontfermeil", "type_entity": "LOC", "lemma": "ClichyMontfermeil", "pos_tag": "ADV", "position": 68, "title": false}, {"word": "Puis", "type_entity": "", "lemma": "Puis", "pos_tag": "CCONJ", "position": 70, "title": false}, {"word": "passe", "type_entity": "", "lemma": "passer", "pos_tag": "VERB", "position": 73, "title": false}, {"word": "Mali", "type_entity": "LOC", "lemma": "Mali", "pos_tag": "PROPN", "position": 77, "title": false}, {"word": "route", "type_entity": "", "lemma": "router", "pos_tag": "NOUN", "position": 80, "title": false}, {"word": "otages", "type_entity": "", "lemma": "otage", "pos_tag": "NOUN", "position": 82, "title": false}, {"word": "ami", "type_entity": "", "lemma": "ami", "pos_tag": "NOUN", "position": 85, "title": false}, {"word": "rappeur", "type_entity": "", "lemma": "rappeur", "pos_tag": "NOUN", "position": 86, "title": false}, {"word": "Said_Belktibia", "type_entity": "PER", "lemma": "Said_Belktibia", "pos_tag": "PUNCT", "position": 87, "title": false}, {"word": "groupe", "type_entity": "", "lemma": "grouper", "pos_tag": "NOUN", "position": 89, "title": false}, {"word": "La_Caution", "type_entity": "ORG", "lemma": "La_Caution", "pos_tag": "NOUN", "position": 90, "title": false}, {"word": "membre", "type_entity": "", "lemma": "membre", "pos_tag": "NOUN", "position": 92, "title": false}, {"word": "Kourtrajme", "type_entity": "LOC", "lemma": "Kourtrajme", "pos_tag": "PROPN", "position": 94, "title": false}, {"word": "ramener", "type_entity": "", "lemma": "ramener", "pos_tag": "VERB", "position": 97, "title": false}, {"word": "documentaire", "type_entity": "", "lemma": "documentaire", "pos_tag": "ADJ", "position": 100, "title": false}, {"word": "sorti", "type_entity": "", "lemma": "sortir", "pos_tag": "NOUN", "position": 101, "title": false}, {"word": "mars2014_365_jours", "type_entity": "MISC", "lemma": "mars2014_365_jours", "pos_tag": "ADJ", "position": 103, "title": false}, {"word": "Mali", "type_entity": "LOC", "lemma": "Mali", "pos_tag": "PROPN", "position": 105, "title": false}, {"word": "disponible", "type_entity": "", "lemma": "disponible", "pos_tag": "ADJ", "position": 107, "title": false}, {"word": "Net", "type_entity": "MISC", "lemma": "Net", "pos_tag": "NOUN", "position": 110, "title": false}, {"word": "Les_Miserables", "type_entity": "MISC", "lemma": "Les_Miserables", "pos_tag": "DET", "position": 112, "title": false}, {"word": "fiction", "type_entity": "", "lemma": "fiction", "pos_tag": "NOUN", "position": 113, "title": false}, {"word": "quinze", "type_entity": "", "lemma": "quinze", "pos_tag": "NUM", "position": 115, "title": false}, {"word": "minutes", "type_entity": "", "lemma": "minuter", "pos_tag": "NOUN", "position": 116, "title": false}, {"word": "raconte", "type_entity": "", "lemma": "raconter", "pos_tag": "VERB", "position": 117, "title": false}, {"word": "bapteme", "type_entity": "", "lemma": "bapteme", "pos_tag": "NOUN", "position": 119, "title": false}, {"word": "feu", "type_entity": "", "lemma": "feu", "pos_tag": "NOUN", "position": 121, "title": false}, {"word": "Pento_Damien_Bonnard", "type_entity": "PER", "lemma": "Pento_Damien_Bonnard", "pos_tag": "NOUN", "position": 123, "title": false}, {"word": "vient", "type_entity": "", "lemma": "venir", "pos_tag": "VERB", "position": 125, "title": false}, {"word": "integrer", "type_entity": "", "lemma": "integrer", "pos_tag": "VERB", "position": 127, "title": false}, {"word": "brigade", "type_entity": "", "lemma": "brigade", "pos_tag": "NOUN", "position": 129, "title": false}, {"word": "anticriminalite", "type_entity": "", "lemma": "anticriminalite", "pos_tag": "ADJ", "position": 130, "title": false}, {"word": "SeineSaintDenis", "type_entity": "LOC", "lemma": "SeineSaintDenis", "pos_tag": "PROPN", "position": 133, "title": false}, {"word": "Du", "type_entity": "", "lemma": "Du", "pos_tag": "DET", "position": 135, "title": false}, {"word": "cinema", "type_entity": "", "lemma": "cinema", "pos_tag": "NOUN", "position": 136, "title": false}, {"word": "verite", "type_entity": "", "lemma": "verite", "pos_tag": "NOUN", "position": 137, "title": false}, {"word": "politique", "type_entity": "", "lemma": "politique", "pos_tag": "ADJ", "position": 138, "title": false}, {"word": "decape", "type_entity": "", "lemma": "decape", "pos_tag": "PROPN", "position": 140, "title": true}, {"word": "denonce", "type_entity": "", "lemma": "denonce", "pos_tag": "NOUN", "position": 142, "title": false}, {"word": "style", "type_entity": "", "lemma": "styler", "pos_tag": "NOUN", "position": 146, "title": false}, {"word": "copwatch", "type_entity": "", "lemma": "copwatch", "pos_tag": "NOUN", "position": 152, "title": false}, {"word": "annees", "type_entity": "", "lemma": "annees", "pos_tag": "NOUN", "position": 155, "title": false}, {"word": "filme", "type_entity": "", "lemma": "filmer", "pos_tag": "VERB", "position": 157, "title": false}, {"word": "bavure", "type_entity": "", "lemma": "bavure", "pos_tag": "NOUN", "position": 159, "title": false}, {"word": "policiere", "type_entity": "", "lemma": "policiere", "pos_tag": "ADJ", "position": 160, "title": false}, {"word": "conduit", "type_entity": "", "lemma": "conduire", "pos_tag": "VERB", "position": 163, "title": false}, {"word": "enquete", "type_entity": "", "lemma": "enquete", "pos_tag": "NOUN", "position": 166, "title": false}, {"word": "IGS", "type_entity": "ORG", "lemma": "IGS", "pos_tag": "PROPN", "position": 169, "title": false}, {"word": "expliquait", "type_entity": "", "lemma": "expliquer", "pos_tag": "VERB", "position": 171, "title": false}, {"word": "Ladj_Ly", "type_entity": "LOC", "lemma": "Ladj_Ly", "pos_tag": "AUX", "position": 172, "title": false}, {"word": "2017", "type_entity": "", "lemma": "2017", "pos_tag": "NUM", "position": 174, "title": false}, {"word": "envie", "type_entity": "", "lemma": "envier", "pos_tag": "NOUN", "position": 178, "title": false}, {"word": "traiter", "type_entity": "", "lemma": "traiter", "pos_tag": "VERB", "position": 180, "title": false}, {"word": "sujet", "type_entity": "", "lemma": "sujet", "pos_tag": "NOUN", "position": 182, "title": false}, {"word": "BAC_Brigade", "type_entity": "MISC", "lemma": "BAC_Brigade", "pos_tag": "NOUN", "position": 185, "title": false}, {"word": "anticriminalite", "type_entity": "", "lemma": "anticriminalite", "pos_tag": "VERB", "position": 186, "title": false}, {"word": "etait", "type_entity": "", "lemma": "etait", "pos_tag": "VERB", "position": 189, "title": false}, {"word": "exercice", "type_entity": "", "lemma": "exercice", "pos_tag": "NOUN", "position": 191, "title": false}, {"word": "style", "type_entity": "", "lemma": "styler", "pos_tag": "NOUN", "position": 193, "title": false}, {"word": "attaquer", "type_entity": "", "lemma": "attaquer", "pos_tag": "VERB", "position": 196, "title": false}, {"word": "long", "type_entity": "", "lemma": "long", "pos_tag": "ADJ", "position": 198, "title": false}, {"word": "metrage", "type_entity": "", "lemma": "metrage", "pos_tag": "NOUN", "position": 199, "title": true}, {"word": "appellera", "type_entity": "", "lemma": "appeler", "pos_tag": "VERB", "position": 204, "title": false}, {"word": "Les_Miserables", "type_entity": "MISC", "lemma": "Les_Miserables", "pos_tag": "ADJ", "position": 205, "title": false}, {"word": "Selectionne", "type_entity": "LOC", "lemma": "Selectionne", "pos_tag": "ADJ", "position": 207, "title": false}, {"word": "2017", "type_entity": "", "lemma": "2017", "pos_tag": "NUM", "position": 209, "title": false}, {"word": "Festival_du_court_metrage", "type_entity": "MISC", "lemma": "Festival_du_court_metrage", "pos_tag": "NOUN", "position": 211, "title": false}, {"word": "ClermontFerrand", "type_entity": "ORG", "lemma": "ClermontFerrand", "pos_tag": "PROPN", "position": 213, "title": false}, {"word": ",", "type_entity": "", "lemma": ",", "pos_tag": "PUNCT", "position": 214, "title": false}, {"word": "film", "type_entity": "", "lemma": "film", "pos_tag": "NOUN", "position": 216, "title": false}, {"word": "obtint", "type_entity": "", "lemma": "obtenir", "pos_tag": "ADJ", "position": 217, "title": false}, {"word": "prix", "type_entity": "", "lemma": "prix", "pos_tag": "NOUN", "position": 219, "title": false}, {"word": "Canal+", "type_entity": "ORG", "lemma": "Canal+", "pos_tag": "ADJ", "position": 220, "title": false}, {"word": "-", "type_entity": "", "lemma": "-", "pos_tag": "PUNCT", "position": 221, "title": false}, {"word": "chaine", "type_entity": "", "lemma": "chaine", "pos_tag": "NOUN", "position": 223, "title": false}, {"word": "pre", "type_entity": "", "lemma": "pre", "pos_tag": "ADV", "position": 228, "title": false}, {"word": "-", "type_entity": "", "lemma": "-", "pos_tag": "PUNCT", "position": 229, "title": false}, {"word": "achete", "type_entity": "", "lemma": "achete", "pos_tag": "NOUN", "position": 230, "title": false}, {"word": ",", "type_entity": "", "lemma": ",", "pos_tag": "PUNCT", "position": 233, "title": false}, {"word": "Les_Miserables", "type_entity": "MISC", "lemma": "Les_Miserables", "pos_tag": "PROPN", "position": 234, "title": false}, {"word": ",", "type_entity": "", "lemma": ",", "pos_tag": "PUNCT", "position": 235, "title": false}, {"word": "produit", "type_entity": "", "lemma": "produire", "pos_tag": "VERB", "position": 236, "title": false}, {"word": "Les_films_du_Worso", "type_entity": "MISC", "lemma": "Les_films_du_Worso", "pos_tag": "NOUN", "position": 238, "title": false}, {"word": "aujourd_hui", "type_entity": "", "lemma": "aujourd_hui", "pos_tag": "ADJ", "position": 240, "title": false}, {"word": "distribue", "type_entity": "", "lemma": "distribuer", "pos_tag": "VERB", "position": 241, "title": false}, {"word": "Salaud_Morisset", "type_entity": "PER", "lemma": "Salaud_Morisset", "pos_tag": "PROPN", "position": 243, "title": false}, {"word": ",", "type_entity": "", "lemma": ",", "pos_tag": "PUNCT", "position": 244, "title": false}, {"word": "ete", "type_entity": "", "lemma": "ete", "pos_tag": "AUX", "position": 246, "title": false}, {"word": "visible", "type_entity": "", "lemma": "visible", "pos_tag": "ADJ", "position": 247, "title": false}, {"word": "dizaines", "type_entity": "", "lemma": "dizaine", "pos_tag": "NOUN", "position": 250, "title": false}, {"word": "festivals", "type_entity": "", "lemma": "festival", "pos_tag": "NOUN", "position": 253, "title": false}, {"word": ",", "type_entity": "", "lemma": ",", "pos_tag": "PUNCT", "position": 254, "title": false}, {"word": "figure", "type_entity": "", "lemma": "figurer", "pos_tag": "VERB", "position": 256, "title": false}, {"word": "liste", "type_entity": "", "lemma": "liste", "pos_tag": "NOUN", "position": 259, "title": false}, {"word": "courts", "type_entity": "", "lemma": "court", "pos_tag": "NOUN", "position": 261, "title": false}, {"word": "pre", "type_entity": "", "lemma": "pre", "pos_tag": "ADV", "position": 262, "title": false}, {"word": "-", "type_entity": "", "lemma": "-", "pos_tag": "PUNCT", "position": 263, "title": false}, {"word": "selectionnes", "type_entity": "", "lemma": "selectionnes", "pos_tag": "VERB", "position": 264, "title": false}, {"word": "Cesar_2018", "type_entity": "MISC", "lemma": "Cesar_2018", "pos_tag": "NOUN", "position": 267, "title": false}, {"word": "Apres", "type_entity": "", "lemma": "Apres", "pos_tag": "NOUN", "position": 269, "title": false}, {"word": "diffuse", "type_entity": "", "lemma": "diffuser", "pos_tag": "VERB", "position": 272, "title": false}, {"word": "premiere", "type_entity": "", "lemma": "premiere", "pos_tag": "ADJ", "position": 274, "title": false}, {"word": "fois", "type_entity": "", "lemma": "foi", "pos_tag": "NOUN", "position": 275, "title": false}, {"word": "Telerama.fr", "type_entity": "LOC", "lemma": "Telerama.fr", "pos_tag": "NOUN", "position": 277, "title": false}, {"word": ",", "type_entity": "", "lemma": ",", "pos_tag": "PUNCT", "position": 283, "title": false}, {"word": "proposons", "type_entity": "", "lemma": "proposer", "pos_tag": "VERB", "position": 286, "title": false}, {"word": "revoir", "type_entity": "", "lemma": "revoir", "pos_tag": "NOUN", "position": 289, "title": false}, {"word": "jusqu", "type_entity": "", "lemma": "jusqu", "pos_tag": "VERB", "position": 290, "title": false}, {"word": "31janvier", "type_entity": "", "lemma": "31janvier", "pos_tag": "NUM", "position": 292, "title": false}, {"word": "Regardez", "type_entity": "LOC", "lemma": "Regardez", "pos_tag": "PROPN", "position": 1, "title": true}, {"word": "Miserables", "type_entity": "", "lemma": "Miserables", "pos_tag": "NOUN", "position": 3, "title": false}, {"word": "Ladj", "type_entity": "", "lemma": "Ladj", "pos_tag": "PROPN", "position": 5, "title": true}, {"word": "Ly", "type_entity": "", "lemma": "Ly", "pos_tag": "DET", "position": 6, "title": false}, {"word": "court", "type_entity": "", "lemma": "courir", "pos_tag": "NOUN", "position": 8, "title": true}, {"word": "metrage", "type_entity": "", "lemma": "metrage", "pos_tag": "NOUN", "position": 9, "title": true}, {"word": "decape", "type_entity": "", "lemma": "decape", "pos_tag": "NOUN", "position": 11, "title": true}], "id_art": "5d7de996f05d51d98d56ed1e4807b3a3", "article": {"surname_author": [], "name_newspaper": " Telerama.fr", "date_publication": "2018-01-10"}}]