{"id_art": "a44615be84af27d9b8a5a9858da5cfbb", "title": "Emmanuel Macron en visite a Calais pour defendre sa politique migratoire", "newspaper": "Le Monde", "author": ["EN LIVE"], "date_publi": "2018-01-16", "content": " Le chef de l'Etat et le gouvernement sont critiques par les associations, la gauche et une partie de la majorite qui estiment que le projet de loi immigration porte atteinte au droit d'asile. Le Monde | 16.01.2018 a 04h29 * Mis a jour le\n16.01.2018 a 08h39 Le chef de l'Etat debutera son deplacement a Croisilles (Pas-de-Calais), ou a ete ouvert l'un des trois centres d'accueil et d'examen de situation (CAES), une nouvelle structure pour heberger les migrants dans l'attente d'une decision administrative sur leur droit a se rendre au Royaume-Uni, a rester en France, a etre renvoye dans le pays d'entree dans l'Union europeenne ou a etre expulse vers leur pays d'origine. En fin de matinee, Emmanuel Macron arrivera a Calais pour sa premiere visite en temps que president. Accompagne de quatre ministres, dont le ministre de l'interieur, Gerard Collomb, et la ministre de la justice, Nicole Belloubet, il y prononcera un discours devant les forces de l'ordre, avant de s'entretenir avec les elus locaux, les acteurs economiques et les associations d'aide aux migrants, et de decouvrir le front de mer en partie rehabilite. Le chef de l'Etat << va tenir un discours de verite : la frontiere est fermee et Calais ne peut plus etre une destination pour les migrants >>, a fait savoir l'Elysee. Lire l'article : << On occulte l'urgence et la necessite qui ont pousse les gens a venir jusqu'a Calais >> La situation dans le principal port transmanche est moins critique qu'il y a quatorze mois, avant la fermeture de la << jungle >>, l'immense campement sauvage ou cohabitaient pres de 8 000 migrants rassembles dans l'espoir de rejoindre les rives britanniques. Elle s'est << amelioree >> mais << n'est pas encore stabilisee >>, resume l'Elysee. Entre 350 et 500 migrants, selon l'Etat, sont toujours presents a Calais, essentiellement venus de la corne de l'Afrique (Ethiopie, Erythree) et d'Afghanistan. Ils survivent dans des conditions difficiles, sans abri fixe, car << les forces de l'ordre ont l'ordre de proceder systematiquement au demantelement des campements sauvages >>, selon l'Elysee. Des associations leur distribuent vetements, duvets et nourriture quotidiennement. Les effectifs des forces de l'ordre ont ete renforces et s'elevent a 1 130 policiers et gendarmes dans le Calaisis, qui interviennent parfois pour stopper des heurts entre groupes de migrants, comme dans la nuit de dimanche a lundi. Pour la maire de Calais, Natacha Bouchart (LR), l'insecurite reste un probleme << quotidien >>. Des migrants << creent des delits permanents. Ils interpellent les transporteurs, ils sautent sur les camions, ils arrachent les baches. (...) Ils mettent en danger leur vie, ils mettent en danger la vie des citoyens calaisiens >>, selon elle. En s'adressant aux forces de l'ordre mardi, Emmanuel Macron << va leur dire de maniere tres claire qu'il faut qu'elles soient exemplaires dans leurs interventions >>, declare l'Elysee. Dans un rapport publie en 2017, l'ONG Human Rights Watch (HRW) avait denonce un usage excessif de la force contre les migrants et des << abus >>, notamment contre des enfants. Lire aussi : Des associations portent plainte contre la confiscation des biens des migrants Deux des principales associations locales d'aide aux migrants, L'Auberge des migrants et Utopia 56, ont, par ailleurs, decide de boycotter la rencontre du monde associatif avec le president. << Alors meme que le gouvernement n'a pas ecoute a Paris les grandes organisations humanitaires, ni sur leurs critiques, ni sur leurs propositions, pourquoi le president tiendrait-il compte des memes critiques et propositions des associations locales ? >>, s'interrogent-elles pour justifier leur refus. Emmanuel Macron ne devrait pas s'exprimer en detail sur le projet de loi asile-migration que M. Collomb doit presenter courant fevrier en conseil des ministres. Le ministre de l'interieur a reaffirme dimanche qu'il n'etait << pas question >> de changer l'orientation du projet de loi, qui est << totalement equilibre >>. En revanche, le president devrait envoyer des messages a Londres a deux jours du sommet franco-britannique avec Theresa May qui se tiendra, jeudi, dans le sud de l'Angleterre. Paris veut obtenir de Londres << des mesures concretes >> pour une meilleure prise en charge des mineurs isoles et pour le financement de la securisation du terminal transmanche et du port de Calais, selon l'Elysee. A cette occasion, les accords du Touquet, qui fixent depuis 2004 la frontiere a Calais, pourraient etre amenages. Gerard Collomb a promis mardi de demander aux Britanniques d'<< aider Calais a se developper >>. << Nous allons avec le president de la Republique jeudi a Londres >> pour << parler de Calais et des problemes d'immigration, pour demander a nos amis britanniques qu'ils puissent aller plus loin dans les accords passes au Touquet >> (fixant la frontiere cote francais) et << qu'ils reprennent un certain nombre de migrants >>, affirme M. Collomb sur France 2. Mais << surtout >> il s'agit de leur demander << qu'ils aident Calais a se developper, pour faire en sorte qu'un certain nombre d'amenagements qui sont prevus par la maire puissent etre finances par la Grande-Bretagne >>, a ajoute M. Collomb. M. Collomb a par ailleurs vigoureusement conteste les accusations de violences policieres envers des migrants lances par des associations. << Je m'inscris en faux contre ces affirmations >> que << personne n'a pu montrer >>, a-t-il affirme, rappelant qu'un recent rapport de l'inspection generale avait conclu << qu'il y avait pu y avoir quelques derapages individuels mais que les forces de police, dans leur generalite, etaient dans un respect fort de la deontologie >>. << Ce sont eux qui tres souvent sont en train de separer les affrontements entre les differents clans de migrants >> car les policiers << protegent plutot qu'ils ne detruisent >> a-t-il dit. A Croisilles, le 13 janvier. Sur les trois centres d'accueil et d'examen des situations des Hauts-de-France, aucun n'est plein. Croisilles affiche le meilleur remplissage, avec 62 lits occupes sur 70. Ce qui n'empeche pas le ministere de l'interieur de se feliciter que << ces centres ont permis de significativement ameliorer la situation la ou ils sont deployes >>. LAURENCE GEAI POUR \"LE MONDE\" Abonnez-vous a partir de 1 EUR Le monde abonnements Profitez du journal ou et quand vous voulez. Abonnements papier, offres 100 % numeriques sur Web et tablette. S'abonner au Monde a partir de 1 EUR Journal d'information en ligne, Le Monde.fr offre a ses visiteurs un panorama complet de l'actualite. Decouvrez chaque jour toute l'info en direct (de la politique a l'economie en passant par le sport et la meteo) sur Le Monde.fr, le site de news leader de la presse francaise en ligne. Le chef de l'Etat et le gouvernement sont critiques par les associations, la gauche et une partie de la majorite qui estiment que le projet de loi immigration porte atteinte au droit d'asile. Le Monde | 16.01.2018 a 04h29 * Mis a jour le\n16.01.2018 a 08h39 Le chef de l'Etat debutera son deplacement a Croisilles (Pas-de-Calais), ou a ete ouvert l'un des trois centres d'accueil et d'examen de situation (CAES), une nouvelle structure pour heberger les migrants dans l'attente d'une decision administrative sur leur droit a se rendre au Royaume-Uni, a rester en France, a etre renvoye dans le pays d'entree dans l'Union europeenne ou a etre expulse vers leur pays d'origine. En fin de matinee, Emmanuel Macron arrivera a Calais pour sa premiere visite en temps que president. Accompagne de quatre ministres, dont le ministre de l'interieur, Gerard Collomb, et la ministre de la justice, Nicole Belloubet, il y prononcera un discours devant les forces de l'ordre, avant de s'entretenir avec les elus locaux, les acteurs economiques et les associations d'aide aux migrants, et de decouvrir le front de mer en partie rehabilite. Le chef de l'Etat << va tenir un discours de verite : la frontiere est fermee et Calais ne peut plus etre une destination pour les migrants >>, a fait savoir l'Elysee. Lire l'article : << On occulte l'urgence et la necessite qui ont pousse les gens a venir jusqu'a Calais >> La situation dans le principal port transmanche est moins critique qu'il y a quatorze mois, avant la fermeture de la << jungle >>, l'immense campement sauvage ou cohabitaient pres de 8 000 migrants rassembles dans l'espoir de rejoindre les rives britanniques. Elle s'est << amelioree >> mais << n'est pas encore stabilisee >>, resume l'Elysee. Entre 350 et 500 migrants, selon l'Etat, sont toujours presents a Calais, essentiellement venus de la corne de l'Afrique (Ethiopie, Erythree) et d'Afghanistan. Ils survivent dans des conditions difficiles, sans abri fixe, car << les forces de l'ordre ont l'ordre de proceder systematiquement au demantelement des campements sauvages >>, selon l'Elysee. Des associations leur distribuent vetements, duvets et nourriture quotidiennement. Les effectifs des forces de l'ordre ont ete renforces et s'elevent a 1 130 policiers et gendarmes dans le Calaisis, qui interviennent parfois pour stopper des heurts entre groupes de migrants, comme dans la nuit de dimanche a lundi. Pour la maire de Calais, Natacha Bouchart (LR), l'insecurite reste un probleme << quotidien >>. Des migrants << creent des delits permanents. Ils interpellent les transporteurs, ils sautent sur les camions, ils arrachent les baches. (...) Ils mettent en danger leur vie, ils mettent en danger la vie des citoyens calaisiens >>, selon elle. En s'adressant aux forces de l'ordre mardi, Emmanuel Macron << va leur dire de maniere tres claire qu'il faut qu'elles soient exemplaires dans leurs interventions >>, declare l'Elysee. Dans un rapport publie en 2017, l'ONG Human Rights Watch (HRW) avait denonce un usage excessif de la force contre les migrants et des << abus >>, notamment contre des enfants. Lire aussi : Des associations portent plainte contre la confiscation des biens des migrants Deux des principales associations locales d'aide aux migrants, L'Auberge des migrants et Utopia 56, ont, par ailleurs, decide de boycotter la rencontre du monde associatif avec le president. << Alors meme que le gouvernement n'a pas ecoute a Paris les grandes organisations humanitaires, ni sur leurs critiques, ni sur leurs propositions, pourquoi le president tiendrait-il compte des memes critiques et propositions des associations locales ? >>, s'interrogent-elles pour justifier leur refus. Emmanuel Macron ne devrait pas s'exprimer en detail sur le projet de loi asile-migration que M. Collomb doit presenter courant fevrier en conseil des ministres. Le ministre de l'interieur a reaffirme dimanche qu'il n'etait << pas question >> de changer l'orientation du projet de loi, qui est << totalement equilibre >>. En revanche, le president devrait envoyer des messages a Londres a deux jours du sommet franco-britannique avec Theresa May qui se tiendra, jeudi, dans le sud de l'Angleterre. Paris veut obtenir de Londres << des mesures concretes >> pour une meilleure prise en charge des mineurs isoles et pour le financement de la securisation du terminal transmanche et du port de Calais, selon l'Elysee. A cette occasion, les accords du Touquet, qui fixent depuis 2004 la frontiere a Calais, pourraient etre amenages. Gerard Collomb a promis mardi de demander aux Britanniques d'<< aider Calais a se developper >>. << Nous allons avec le president de la Republique jeudi a Londres >> pour << parler de Calais et des problemes d'immigration, pour demander a nos amis britanniques qu'ils puissent aller plus loin dans les accords passes au Touquet >> (fixant la frontiere cote francais) et << qu'ils reprennent un certain nombre de migrants >>, affirme M. Collomb sur France 2. Mais << surtout >> il s'agit de leur demander << qu'ils aident Calais a se developper, pour faire en sorte qu'un certain nombre d'amenagements qui sont prevus par la maire puissent etre finances par la Grande-Bretagne >>, a ajoute M. Collomb. M. Collomb a par ailleurs vigoureusement conteste les accusations de violences policieres envers des migrants lances par des associations. << Je m'inscris en faux contre ces affirmations >> que << personne n'a pu montrer >>, a-t-il affirme, rappelant qu'un recent rapport de l'inspection generale avait conclu << qu'il y avait pu y avoir quelques derapages individuels mais que les forces de police, dans leur generalite, etaient dans un respect fort de la deontologie >>. << Ce sont eux qui tres souvent sont en train de separer les affrontements entre les differents clans de migrants >> car les policiers << protegent plutot qu'ils ne detruisent >> a-t-il dit. A Croisilles, le 13 janvier. Sur les trois centres d'accueil et d'examen des situations des Hauts-de-France, aucun n'est plein. Croisilles affiche le meilleur remplissage, avec 62 lits occupes sur 70. Ce qui n'empeche pas le ministere de l'interieur de se feliciter que << ces centres ont permis de significativement ameliorer la situation la ou ils sont deployes >>. LAURENCE GEAI POUR \"LE MONDE\" Abonnez-vous a partir de 1 EUR Le chef de l'Etat et le gouvernement sont critiques par les associations, la gauche et une partie de la majorite qui estiment que le projet de loi immigration porte atteinte au droit d'asile. Le Monde | 16.01.2018 a 04h29 * Mis a jour le\n16.01.2018 a 08h39 Le chef de l'Etat debutera son deplacement a Croisilles (Pas-de-Calais), ou a ete ouvert l'un des trois centres d'accueil et d'examen de situation (CAES), une nouvelle structure pour heberger les migrants dans l'attente d'une decision administrative sur leur droit a se rendre au Royaume-Uni, a rester en France, a etre renvoye dans le pays d'entree dans l'Union europeenne ou a etre expulse vers leur pays d'origine. En fin de matinee, Emmanuel Macron arrivera a Calais pour sa premiere visite en temps que president. Accompagne de quatre ministres, dont le ministre de l'interieur, Gerard Collomb, et la ministre de la justice, Nicole Belloubet, il y prononcera un discours devant les forces de l'ordre, avant de s'entretenir avec les elus locaux, les acteurs economiques et les associations d'aide aux migrants, et de decouvrir le front de mer en partie rehabilite. Le chef de l'Etat << va tenir un discours de verite : la frontiere est fermee et Calais ne peut plus etre une destination pour les migrants >>, a fait savoir l'Elysee. Lire l'article : << On occulte l'urgence et la necessite qui ont pousse les gens a venir jusqu'a Calais >> La situation dans le principal port transmanche est moins critique qu'il y a quatorze mois, avant la fermeture de la << jungle >>, l'immense campement sauvage ou cohabitaient pres de 8 000 migrants rassembles dans l'espoir de rejoindre les rives britanniques. Elle s'est << amelioree >> mais << n'est pas encore stabilisee >>, resume l'Elysee. Entre 350 et 500 migrants, selon l'Etat, sont toujours presents a Calais, essentiellement venus de la corne de l'Afrique (Ethiopie, Erythree) et d'Afghanistan. Ils survivent dans des conditions difficiles, sans abri fixe, car << les forces de l'ordre ont l'ordre de proceder systematiquement au demantelement des campements sauvages >>, selon l'Elysee. Des associations leur distribuent vetements, duvets et nourriture quotidiennement. Les effectifs des forces de l'ordre ont ete renforces et s'elevent a 1 130 policiers et gendarmes dans le Calaisis, qui interviennent parfois pour stopper des heurts entre groupes de migrants, comme dans la nuit de dimanche a lundi. Pour la maire de Calais, Natacha Bouchart (LR), l'insecurite reste un probleme << quotidien >>. Des migrants << creent des delits permanents. Ils interpellent les transporteurs, ils sautent sur les camions, ils arrachent les baches. (...) Ils mettent en danger leur vie, ils mettent en danger la vie des citoyens calaisiens >>, selon elle. En s'adressant aux forces de l'ordre mardi, Emmanuel Macron << va leur dire de maniere tres claire qu'il faut qu'elles soient exemplaires dans leurs interventions >>, declare l'Elysee. Dans un rapport publie en 2017, l'ONG Human Rights Watch (HRW) avait denonce un usage excessif de la force contre les migrants et des << abus >>, notamment contre des enfants. Lire aussi : Des associations portent plainte contre la confiscation des biens des migrants Deux des principales associations locales d'aide aux migrants, L'Auberge des migrants et Utopia 56, ont, par ailleurs, decide de boycotter la rencontre du monde associatif avec le president. << Alors meme que le gouvernement n'a pas ecoute a Paris les grandes organisations humanitaires, ni sur leurs critiques, ni sur leurs propositions, pourquoi le president tiendrait-il compte des memes critiques et propositions des associations locales ? >>, s'interrogent-elles pour justifier leur refus. Emmanuel Macron ne devrait pas s'exprimer en detail sur le projet de loi asile-migration que M. Collomb doit presenter courant fevrier en conseil des ministres. Le ministre de l'interieur a reaffirme dimanche qu'il n'etait << pas question >> de changer l'orientation du projet de loi, qui est << totalement equilibre >>. En revanche, le president devrait envoyer des messages a Londres a deux jours du sommet franco-britannique avec Theresa May qui se tiendra, jeudi, dans le sud de l'Angleterre. Paris veut obtenir de Londres << des mesures concretes >> pour une meilleure prise en charge des mineurs isoles et pour le financement de la securisation du terminal transmanche et du port de Calais, selon l'Elysee. A cette occasion, les accords du Touquet, qui fixent depuis 2004 la frontiere a Calais, pourraient etre amenages. Gerard Collomb a promis mardi de demander aux Britanniques d'<< aider Calais a se developper >>. << Nous allons avec le president de la Republique jeudi a Londres >> pour << parler de Calais et des problemes d'immigration, pour demander a nos amis britanniques qu'ils puissent aller plus loin dans les accords passes au Touquet >> (fixant la frontiere cote francais) et << qu'ils reprennent un certain nombre de migrants >>, affirme M. Collomb sur France 2. Mais << surtout >> il s'agit de leur demander << qu'ils aident Calais a se developper, pour faire en sorte qu'un certain nombre d'amenagements qui sont prevus par la maire puissent etre finances par la Grande-Bretagne >>, a ajoute M. Collomb. M. Collomb a par ailleurs vigoureusement conteste les accusations de violences policieres envers des migrants lances par des associations. << Je m'inscris en faux contre ces affirmations >> que << personne n'a pu montrer >>, a-t-il affirme, rappelant qu'un recent rapport de l'inspection generale avait conclu << qu'il y avait pu y avoir quelques derapages individuels mais que les forces de police, dans leur generalite, etaient dans un respect fort de la deontologie >>. << Ce sont eux qui tres souvent sont en train de separer les affrontements entre les differents clans de migrants >> car les policiers << protegent plutot qu'ils ne detruisent >> a-t-il dit. A Croisilles, le 13 janvier. Sur les trois centres d'accueil et d'examen des situations des Hauts-de-France, aucun n'est plein. Croisilles affiche le meilleur remplissage, avec 62 lits occupes sur 70. Ce qui n'empeche pas le ministere de l'interieur de se feliciter que << ces centres ont permis de significativement ameliorer la situation la ou ils sont deployes >>. LAURENCE GEAI POUR \"LE MONDE\" Abonnez-vous a partir de 1 EUR Le chef de l'Etat et le gouvernement sont critiques par les associations, la gauche et une partie de la majorite qui estiment que le projet de loi immigration porte atteinte au droit d'asile. Le Monde | 16.01.2018 a 04h29 * Mis a jour le\n16.01.2018 a 08h39 Le chef de l'Etat debutera son deplacement a Croisilles (Pas-de-Calais), ou a ete ouvert l'un des trois centres d'accueil et d'examen de situation (CAES), une nouvelle structure pour heberger les migrants dans l'attente d'une decision administrative sur leur droit a se rendre au Royaume-Uni, a rester en France, a etre renvoye dans le pays d'entree dans l'Union europeenne ou a etre expulse vers leur pays d'origine. En fin de matinee, Emmanuel Macron arrivera a Calais pour sa premiere visite en temps que president. Accompagne de quatre ministres, dont le ministre de l'interieur, Gerard Collomb, et la ministre de la justice, Nicole Belloubet, il y prononcera un discours devant les forces de l'ordre, avant de s'entretenir avec les elus locaux, les acteurs economiques et les associations d'aide aux migrants, et de decouvrir le front de mer en partie rehabilite. Le chef de l'Etat << va tenir un discours de verite : la frontiere est fermee et Calais ne peut plus etre une destination pour les migrants >>, a fait savoir l'Elysee. Lire l'article : << On occulte l'urgence et la necessite qui ont pousse les gens a venir jusqu'a Calais >> La situation dans le principal port transmanche est moins critique qu'il y a quatorze mois, avant la fermeture de la << jungle >>, l'immense campement sauvage ou cohabitaient pres de 8 000 migrants rassembles dans l'espoir de rejoindre les rives britanniques. Elle s'est << amelioree >> mais << n'est pas encore stabilisee >>, resume l'Elysee. Entre 350 et 500 migrants, selon l'Etat, sont toujours presents a Calais, essentiellement venus de la corne de l'Afrique (Ethiopie, Erythree) et d'Afghanistan. Ils survivent dans des conditions difficiles, sans abri fixe, car << les forces de l'ordre ont l'ordre de proceder systematiquement au demantelement des campements sauvages >>, selon l'Elysee. Des associations leur distribuent vetements, duvets et nourriture quotidiennement. Les effectifs des forces de l'ordre ont ete renforces et s'elevent a 1 130 policiers et gendarmes dans le Calaisis, qui interviennent parfois pour stopper des heurts entre groupes de migrants, comme dans la nuit de dimanche a lundi. Pour la maire de Calais, Natacha Bouchart (LR), l'insecurite reste un probleme << quotidien >>. Des migrants << creent des delits permanents. Ils interpellent les transporteurs, ils sautent sur les camions, ils arrachent les baches. (...) Ils mettent en danger leur vie, ils mettent en danger la vie des citoyens calaisiens >>, selon elle. En s'adressant aux forces de l'ordre mardi, Emmanuel Macron << va leur dire de maniere tres claire qu'il faut qu'elles soient exemplaires dans leurs interventions >>, declare l'Elysee. Dans un rapport publie en 2017, l'ONG Human Rights Watch (HRW) avait denonce un usage excessif de la force contre les migrants et des << abus >>, notamment contre des enfants. Lire aussi : Des associations portent plainte contre la confiscation des biens des migrants Deux des principales associations locales d'aide aux migrants, L'Auberge des migrants et Utopia 56, ont, par ailleurs, decide de boycotter la rencontre du monde associatif avec le president. << Alors meme que le gouvernement n'a pas ecoute a Paris les grandes organisations humanitaires, ni sur leurs critiques, ni sur leurs propositions, pourquoi le president tiendrait-il compte des memes critiques et propositions des associations locales ? >>, s'interrogent-elles pour justifier leur refus. Emmanuel Macron ne devrait pas s'exprimer en detail sur le projet de loi asile-migration que M. Collomb doit presenter courant fevrier en conseil des ministres. Le ministre de l'interieur a reaffirme dimanche qu'il n'etait << pas question >> de changer l'orientation du projet de loi, qui est << totalement equilibre >>. En revanche, le president devrait envoyer des messages a Londres a deux jours du sommet franco-britannique avec Theresa May qui se tiendra, jeudi, dans le sud de l'Angleterre. Paris veut obtenir de Londres << des mesures concretes >> pour une meilleure prise en charge des mineurs isoles et pour le financement de la securisation du terminal transmanche et du port de Calais, selon l'Elysee. A cette occasion, les accords du Touquet, qui fixent depuis 2004 la frontiere a Calais, pourraient etre amenages. Gerard Collomb a promis mardi de demander aux Britanniques d'<< aider Calais a se developper >>. << Nous allons avec le president de la Republique jeudi a Londres >> pour << parler de Calais et des problemes d'immigration, pour demander a nos amis britanniques qu'ils puissent aller plus loin dans les accords passes au Touquet >> (fixant la frontiere cote francais) et << qu'ils reprennent un certain nombre de migrants >>, affirme M. Collomb sur France 2. Mais << surtout >> il s'agit de leur demander << qu'ils aident Calais a se developper, pour faire en sorte qu'un certain nombre d'amenagements qui sont prevus par la maire puissent etre finances par la Grande-Bretagne >>, a ajoute M. Collomb. M. Collomb a par ailleurs vigoureusement conteste les accusations de violences policieres envers des migrants lances par des associations. << Je m'inscris en faux contre ces affirmations >> que << personne n'a pu montrer >>, a-t-il affirme, rappelant qu'un recent rapport de l'inspection generale avait conclu << qu'il y avait pu y avoir quelques derapages individuels mais que les forces de police, dans leur generalite, etaient dans un respect fort de la deontologie >>. << Ce sont eux qui tres souvent sont en train de separer les affrontements entre les differents clans de migrants >> car les policiers << protegent plutot qu'ils ne detruisent >> a-t-il dit. A Croisilles, le 13 janvier. Sur les trois centres d'accueil et d'examen des situations des Hauts-de-France, aucun n'est plein. Croisilles affiche le meilleur remplissage, avec 62 lits occupes sur 70. Ce qui n'empeche pas le ministere de l'interieur de se feliciter que << ces centres ont permis de significativement ameliorer la situation la ou ils sont deployes >>. LAURENCE GEAI POUR \"LE MONDE\" Abonnez-vous a partir de 1 EUR Le chef de l'Etat et le gouvernement sont critiques par les associations, la gauche et une partie de la majorite qui estiment que le projet de loi immigration porte atteinte au droit d'asile. Le Monde | 16.01.2018 a 04h29 * Mis a jour le\n16.01.2018 a 08h39 Le chef de l'Etat debutera son deplacement a Croisilles (Pas-de-Calais), ou a ete ouvert l'un des trois centres d'accueil et d'examen de situation (CAES), une nouvelle structure pour heberger les migrants dans l'attente d'une decision administrative sur leur droit a se rendre au Royaume-Uni, a rester en France, a etre renvoye dans le pays d'entree dans l'Union europeenne ou a etre expulse vers leur pays d'origine. En fin de matinee, Emmanuel Macron arrivera a Calais pour sa premiere visite en temps que president. Accompagne de quatre ministres, dont le ministre de l'interieur, Gerard Collomb, et la ministre de la justice, Nicole Belloubet, il y prononcera un discours devant les forces de l'ordre, avant de s'entretenir avec les elus locaux, les acteurs economiques et les associations d'aide aux migrants, et de decouvrir le front de mer en partie rehabilite. Le chef de l'Etat << va tenir un discours de verite : la frontiere est fermee et Calais ne peut plus etre une destination pour les migrants >>, a fait savoir l'Elysee. Lire l'article : << On occulte l'urgence et la necessite qui ont pousse les gens a venir jusqu'a Calais >> La situation dans le principal port transmanche est moins critique qu'il y a quatorze mois, avant la fermeture de la << jungle >>, l'immense campement sauvage ou cohabitaient pres de 8 000 migrants rassembles dans l'espoir de rejoindre les rives britanniques. Elle s'est << amelioree >> mais << n'est pas encore stabilisee >>, resume l'Elysee. Entre 350 et 500 migrants, selon l'Etat, sont toujours presents a Calais, essentiellement venus de la corne de l'Afrique (Ethiopie, Erythree) et d'Afghanistan. Ils survivent dans des conditions difficiles, sans abri fixe, car << les forces de l'ordre ont l'ordre de proceder systematiquement au demantelement des campements sauvages >>, selon l'Elysee. Des associations leur distribuent vetements, duvets et nourriture quotidiennement. Les effectifs des forces de l'ordre ont ete renforces et s'elevent a 1 130 policiers et gendarmes dans le Calaisis, qui interviennent parfois pour stopper des heurts entre groupes de migrants, comme dans la nuit de dimanche a lundi. Pour la maire de Calais, Natacha Bouchart (LR), l'insecurite reste un probleme << quotidien >>. Des migrants << creent des delits permanents. Ils interpellent les transporteurs, ils sautent sur les camions, ils arrachent les baches. (...) Ils mettent en danger leur vie, ils mettent en danger la vie des citoyens calaisiens >>, selon elle. En s'adressant aux forces de l'ordre mardi, Emmanuel Macron << va leur dire de maniere tres claire qu'il faut qu'elles soient exemplaires dans leurs interventions >>, declare l'Elysee. Dans un rapport publie en 2017, l'ONG Human Rights Watch (HRW) avait denonce un usage excessif de la force contre les migrants et des << abus >>, notamment contre des enfants. Lire aussi : Des associations portent plainte contre la confiscation des biens des migrants Deux des principales associations locales d'aide aux migrants, L'Auberge des migrants et Utopia 56, ont, par ailleurs, decide de boycotter la rencontre du monde associatif avec le president. << Alors meme que le gouvernement n'a pas ecoute a Paris les grandes organisations humanitaires, ni sur leurs critiques, ni sur leurs propositions, pourquoi le president tiendrait-il compte des memes critiques et propositions des associations locales ? >>, s'interrogent-elles pour justifier leur refus. Emmanuel Macron ne devrait pas s'exprimer en detail sur le projet de loi asile-migration que M. Collomb doit presenter courant fevrier en conseil des ministres. Le ministre de l'interieur a reaffirme dimanche qu'il n'etait << pas question >> de changer l'orientation du projet de loi, qui est << totalement equilibre >>. En revanche, le president devrait envoyer des messages a Londres a deux jours du sommet franco-britannique avec Theresa May qui se tiendra, jeudi, dans le sud de l'Angleterre. Paris veut obtenir de Londres << des mesures concretes >> pour une meilleure prise en charge des mineurs isoles et pour le financement de la securisation du terminal transmanche et du port de Calais, selon l'Elysee. A cette occasion, les accords du Touquet, qui fixent depuis 2004 la frontiere a Calais, pourraient etre amenages. Gerard Collomb a promis mardi de demander aux Britanniques d'<< aider Calais a se developper >>. << Nous allons avec le president de la Republique jeudi a Londres >> pour << parler de Calais et des problemes d'immigration, pour demander a nos amis britanniques qu'ils puissent aller plus loin dans les accords passes au Touquet >> (fixant la frontiere cote francais) et << qu'ils reprennent un certain nombre de migrants >>, affirme M. Collomb sur France 2. Mais << surtout >> il s'agit de leur demander << qu'ils aident Calais a se developper, pour faire en sorte qu'un certain nombre d'amenagements qui sont prevus par la maire puissent etre finances par la Grande-Bretagne >>, a ajoute M. Collomb. M. Collomb a par ailleurs vigoureusement conteste les accusations de violences policieres envers des migrants lances par des associations. << Je m'inscris en faux contre ces affirmations >> que << personne n'a pu montrer >>, a-t-il affirme, rappelant qu'un recent rapport de l'inspection generale avait conclu << qu'il y avait pu y avoir quelques derapages individuels mais que les forces de police, dans leur generalite, etaient dans un respect fort de la deontologie >>. << Ce sont eux qui tres souvent sont en train de separer les affrontements entre les differents clans de migrants >> car les policiers << protegent plutot qu'ils ne detruisent >> a-t-il dit. A Croisilles, le 13 janvier. Sur les trois centres d'accueil et d'examen des situations des Hauts-de-France, aucun n'est plein. Croisilles affiche le meilleur remplissage, avec 62 lits occupes sur 70. Ce qui n'empeche pas le ministere de l'interieur de se feliciter que << ces centres ont permis de significativement ameliorer la situation la ou ils sont deployes >>. LAURENCE GEAI POUR \"LE MONDE\" Le chef de l'Etat et le gouvernement sont critiques par les associations, la gauche et une partie de la majorite qui estiment que le projet de loi immigration porte atteinte au droit d'asile. Le Monde | 16.01.2018 a 04h29 * Mis a jour le\n16.01.2018 a 08h39 Le chef de l'Etat debutera son deplacement a Croisilles (Pas-de-Calais), ou a ete ouvert l'un des trois centres d'accueil et d'examen de situation (CAES), une nouvelle structure pour heberger les migrants dans l'attente d'une decision administrative sur leur droit a se rendre au Royaume-Uni, a rester en France, a etre renvoye dans le pays d'entree dans l'Union europeenne ou a etre expulse vers leur pays d'origine. En fin de matinee, Emmanuel Macron arrivera a Calais pour sa premiere visite en temps que president. Accompagne de quatre ministres, dont le ministre de l'interieur, Gerard Collomb, et la ministre de la justice, Nicole Belloubet, il y prononcera un discours devant les forces de l'ordre, avant de s'entretenir avec les elus locaux, les acteurs economiques et les associations d'aide aux migrants, et de decouvrir le front de mer en partie rehabilite. Le chef de l'Etat << va tenir un discours de verite : la frontiere est fermee et Calais ne peut plus etre une destination pour les migrants >>, a fait savoir l'Elysee. Lire l'article : << On occulte l'urgence et la necessite qui ont pousse les gens a venir jusqu'a Calais >> La situation dans le principal port transmanche est moins critique qu'il y a quatorze mois, avant la fermeture de la << jungle >>, l'immense campement sauvage ou cohabitaient pres de 8 000 migrants rassembles dans l'espoir de rejoindre les rives britanniques. Elle s'est << amelioree >> mais << n'est pas encore stabilisee >>, resume l'Elysee. Entre 350 et 500 migrants, selon l'Etat, sont toujours presents a Calais, essentiellement venus de la corne de l'Afrique (Ethiopie, Erythree) et d'Afghanistan. Ils survivent dans des conditions difficiles, sans abri fixe, car << les forces de l'ordre ont l'ordre de proceder systematiquement au demantelement des campements sauvages >>, selon l'Elysee. Des associations leur distribuent vetements, duvets et nourriture quotidiennement. Les effectifs des forces de l'ordre ont ete renforces et s'elevent a 1 130 policiers et gendarmes dans le Calaisis, qui interviennent parfois pour stopper des heurts entre groupes de migrants, comme dans la nuit de dimanche a lundi. Pour la maire de Calais, Natacha Bouchart (LR), l'insecurite reste un probleme << quotidien >>. Des migrants << creent des delits permanents. Ils interpellent les transporteurs, ils sautent sur les camions, ils arrachent les baches. (...) Ils mettent en danger leur vie, ils mettent en danger la vie des citoyens calaisiens >>, selon elle. En s'adressant aux forces de l'ordre mardi, Emmanuel Macron << va leur dire de maniere tres claire qu'il faut qu'elles soient exemplaires dans leurs interventions >>, declare l'Elysee. Dans un rapport publie en 2017, l'ONG Human Rights Watch (HRW) avait denonce un usage excessif de la force contre les migrants et des << abus >>, notamment contre des enfants. Lire aussi : Des associations portent plainte contre la confiscation des biens des migrants Deux des principales associations locales d'aide aux migrants, L'Auberge des migrants et Utopia 56, ont, par ailleurs, decide de boycotter la rencontre du monde associatif avec le president. << Alors meme que le gouvernement n'a pas ecoute a Paris les grandes organisations humanitaires, ni sur leurs critiques, ni sur leurs propositions, pourquoi le president tiendrait-il compte des memes critiques et propositions des associations locales ? >>, s'interrogent-elles pour justifier leur refus. Emmanuel Macron ne devrait pas s'exprimer en detail sur le projet de loi asile-migration que M. Collomb doit presenter courant fevrier en conseil des ministres. Le ministre de l'interieur a reaffirme dimanche qu'il n'etait << pas question >> de changer l'orientation du projet de loi, qui est << totalement equilibre >>. En revanche, le president devrait envoyer des messages a Londres a deux jours du sommet franco-britannique avec Theresa May qui se tiendra, jeudi, dans le sud de l'Angleterre. Paris veut obtenir de Londres << des mesures concretes >> pour une meilleure prise en charge des mineurs isoles et pour le financement de la securisation du terminal transmanche et du port de Calais, selon l'Elysee. A cette occasion, les accords du Touquet, qui fixent depuis 2004 la frontiere a Calais, pourraient etre amenages. Gerard Collomb a promis mardi de demander aux Britanniques d'<< aider Calais a se developper >>. << Nous allons avec le president de la Republique jeudi a Londres >> pour << parler de Calais et des problemes d'immigration, pour demander a nos amis britanniques qu'ils puissent aller plus loin dans les accords passes au Touquet >> (fixant la frontiere cote francais) et << qu'ils reprennent un certain nombre de migrants >>, affirme M. Collomb sur France 2. Mais << surtout >> il s'agit de leur demander << qu'ils aident Calais a se developper, pour faire en sorte qu'un certain nombre d'amenagements qui sont prevus par la maire puissent etre finances par la Grande-Bretagne >>, a ajoute M. Collomb. M. Collomb a par ailleurs vigoureusement conteste les accusations de violences policieres envers des migrants lances par des associations. << Je m'inscris en faux contre ces affirmations >> que << personne n'a pu montrer >>, a-t-il affirme, rappelant qu'un recent rapport de l'inspection generale avait conclu << qu'il y avait pu y avoir quelques derapages individuels mais que les forces de police, dans leur generalite, etaient dans un respect fort de la deontologie >>. << Ce sont eux qui tres souvent sont en train de separer les affrontements entre les differents clans de migrants >> car les policiers << protegent plutot qu'ils ne detruisent >> a-t-il dit. A Croisilles, le 13 janvier. Sur les trois centres d'accueil et d'examen des situations des Hauts-de-France, aucun n'est plein. Croisilles affiche le meilleur remplissage, avec 62 lits occupes sur 70. Ce qui n'empeche pas le ministere de l'interieur de se feliciter que << ces centres ont permis de significativement ameliorer la situation la ou ils sont deployes >>. LAURENCE GEAI POUR \"LE MONDE\" Le chef de l'Etat debutera son deplacement a Croisilles (Pas-de-Calais), ou a ete ouvert l'un des trois centres d'accueil et d'examen de situation (CAES), une nouvelle structure pour heberger les migrants dans l'attente d'une decision administrative sur leur droit a se rendre au Royaume-Uni, a rester en France, a etre renvoye dans le pays d'entree dans l'Union europeenne ou a etre expulse vers leur pays d'origine. En fin de matinee, Emmanuel Macron arrivera a Calais pour sa premiere visite en temps que president. Accompagne de quatre ministres, dont le ministre de l'interieur, Gerard Collomb, et la ministre de la justice, Nicole Belloubet, il y prononcera un discours devant les forces de l'ordre, avant de s'entretenir avec les elus locaux, les acteurs economiques et les associations d'aide aux migrants, et de decouvrir le front de mer en partie rehabilite. Le chef de l'Etat << va tenir un discours de verite : la frontiere est fermee et Calais ne peut plus etre une destination pour les migrants >>, a fait savoir l'Elysee. Lire l'article : << On occulte l'urgence et la necessite qui ont pousse les gens a venir jusqu'a Calais >> La situation dans le principal port transmanche est moins critique qu'il y a quatorze mois, avant la fermeture de la << jungle >>, l'immense campement sauvage ou cohabitaient pres de 8 000 migrants rassembles dans l'espoir de rejoindre les rives britanniques. Elle s'est << amelioree >> mais << n'est pas encore stabilisee >>, resume l'Elysee. Entre 350 et 500 migrants, selon l'Etat, sont toujours presents a Calais, essentiellement venus de la corne de l'Afrique (Ethiopie, Erythree) et d'Afghanistan. Ils survivent dans des conditions difficiles, sans abri fixe, car << les forces de l'ordre ont l'ordre de proceder systematiquement au demantelement des campements sauvages >>, selon l'Elysee. Des associations leur distribuent vetements, duvets et nourriture quotidiennement. Les effectifs des forces de l'ordre ont ete renforces et s'elevent a 1 130 policiers et gendarmes dans le Calaisis, qui interviennent parfois pour stopper des heurts entre groupes de migrants, comme dans la nuit de dimanche a lundi. Pour la maire de Calais, Natacha Bouchart (LR), l'insecurite reste un probleme << quotidien >>. Des migrants << creent des delits permanents. Ils interpellent les transporteurs, ils sautent sur les camions, ils arrachent les baches. (...) Ils mettent en danger leur vie, ils mettent en danger la vie des citoyens calaisiens >>, selon elle. En s'adressant aux forces de l'ordre mardi, Emmanuel Macron << va leur dire de maniere tres claire qu'il faut qu'elles soient exemplaires dans leurs interventions >>, declare l'Elysee. Dans un rapport publie en 2017, l'ONG Human Rights Watch (HRW) avait denonce un usage excessif de la force contre les migrants et des << abus >>, notamment contre des enfants. Lire aussi : Des associations portent plainte contre la confiscation des biens des migrants Deux des principales associations locales d'aide aux migrants, L'Auberge des migrants et Utopia 56, ont, par ailleurs, decide de boycotter la rencontre du monde associatif avec le president. << Alors meme que le gouvernement n'a pas ecoute a Paris les grandes organisations humanitaires, ni sur leurs critiques, ni sur leurs propositions, pourquoi le president tiendrait-il compte des memes critiques et propositions des associations locales ? >>, s'interrogent-elles pour justifier leur refus. Emmanuel Macron ne devrait pas s'exprimer en detail sur le projet de loi asile-migration que M. Collomb doit presenter courant fevrier en conseil des ministres. Le ministre de l'interieur a reaffirme dimanche qu'il n'etait << pas question >> de changer l'orientation du projet de loi, qui est << totalement equilibre >>. En revanche, le president devrait envoyer des messages a Londres a deux jours du sommet franco-britannique avec Theresa May qui se tiendra, jeudi, dans le sud de l'Angleterre. Paris veut obtenir de Londres << des mesures concretes >> pour une meilleure prise en charge des mineurs isoles et pour le financement de la securisation du terminal transmanche et du port de Calais, selon l'Elysee. A cette occasion, les accords du Touquet, qui fixent depuis 2004 la frontiere a Calais, pourraient etre amenages. Gerard Collomb a promis mardi de demander aux Britanniques d'<< aider Calais a se developper >>. << Nous allons avec le president de la Republique jeudi a Londres >> pour << parler de Calais et des problemes d'immigration, pour demander a nos amis britanniques qu'ils puissent aller plus loin dans les accords passes au Touquet >> (fixant la frontiere cote francais) et << qu'ils reprennent un certain nombre de migrants >>, affirme M. Collomb sur France 2. Mais << surtout >> il s'agit de leur demander << qu'ils aident Calais a se developper, pour faire en sorte qu'un certain nombre d'amenagements qui sont prevus par la maire puissent etre finances par la Grande-Bretagne >>, a ajoute M. Collomb. M. Collomb a par ailleurs vigoureusement conteste les accusations de violences policieres envers des migrants lances par des associations. << Je m'inscris en faux contre ces affirmations >> que << personne n'a pu montrer >>, a-t-il affirme, rappelant qu'un recent rapport de l'inspection generale avait conclu << qu'il y avait pu y avoir quelques derapages individuels mais que les forces de police, dans leur generalite, etaient dans un respect fort de la deontologie >>. << Ce sont eux qui tres souvent sont en train de separer les affrontements entre les differents clans de migrants >> car les policiers << protegent plutot qu'ils ne detruisent >> a-t-il dit. A Croisilles, le 13 janvier. Sur les trois centres d'accueil et d'examen des situations des Hauts-de-France, aucun n'est plein. Croisilles affiche le meilleur remplissage, avec 62 lits occupes sur 70. Ce qui n'empeche pas le ministere de l'interieur de se feliciter que << ces centres ont permis de significativement ameliorer la situation la ou ils sont deployes >>. LAURENCE GEAI POUR \"LE MONDE\" A Croisilles, le 13 janvier. Sur les trois centres d'accueil et d'examen des situations des Hauts-de-France, aucun n'est plein. Croisilles affiche le meilleur remplissage, avec 62 lits occupes sur 70. Ce qui n'empeche pas le ministere de l'interieur de se feliciter que << ces centres ont permis de significativement ameliorer la situation la ou ils sont deployes >>. LAURENCE GEAI POUR \"LE MONDE\" A Croisilles, le 13 janvier. Sur les trois centres d'accueil et d'examen des situations des Hauts-de-France, aucun n'est plein. Croisilles affiche le meilleur remplissage, avec 62 lits occupes sur 70. Ce qui n'empeche pas le ministere de l'interieur de se feliciter que << ces centres ont permis de significativement ameliorer la situation la ou ils sont deployes >>. LAURENCE GEAI POUR \"LE MONDE\" A Croisilles, le 13 janvier. Sur les trois centres d'accueil et d'examen des situations des Hauts-de-France, aucun n'est plein. Croisilles affiche le meilleur remplissage, avec 62 lits occupes sur 70. Ce qui n'empeche pas le ministere de l'interieur de se feliciter que << ces centres ont permis de significativement ameliorer la situation la ou ils sont deployes >>. Abonnez-vous a partir de 1 EUR Abonnez-vous a partir de 1 EUR Le monde abonnements Profitez du journal ou et quand vous voulez. Abonnements papier, offres 100 % numeriques sur Web et tablette. S'abonner au Monde a partir de 1 EUR Le monde abonnements Profitez du journal ou et quand vous voulez. Abonnements papier, offres 100 % numeriques sur Web et tablette. S'abonner au Monde a partir de 1 EUR Le monde abonnements Profitez du journal ou et quand vous voulez. Abonnements papier, offres 100 % numeriques sur Web et tablette. S'abonner au Monde a partir de 1 EUR ", "theme": "Societe"}