{"theme": "Notre-Dame-des-Landes", "id_art": "4209fd0f7c40e5f31313065c0d41f27f", "title": "Notre-Dame-des-Landes : plus de 400 gendarmes deployes autour de la ZAD", "date_publi": "2018-01-17", "content": {"1": {"word": "Journee_cruciale", "type_entity": "MISC", "lemma": "Journee_cruciale", "pos_tag": "ADJ", "position": 1, "title": false}, "2": {"word": "a", "type_entity": "", "lemma": "avoir", "pos_tag": "STOPWORD", "position": 2, "title": false}, "3": {"word": "NotreDamedesLandes", "type_entity": "", "lemma": "NotreDamedesLandes", "pos_tag": "ADJ", "position": 3, "title": false}, "4": {"word": ".", "type_entity": "", "lemma": ".", "pos_tag": "PUNCT", "position": 4, "title": false}, "5": {"word": "Le", "type_entity": "", "lemma": "Le", "pos_tag": "STOPWORD", "position": 5, "title": false}, "6": {"word": "dispositif", "type_entity": "", "lemma": "dispositif", "pos_tag": "NOUN", "position": 6, "title": false}, "7": {"word": "policier", "type_entity": "", "lemma": "policier", "pos_tag": "ADJ", "position": 7, "title": false}, "8": {"word": "se", "type_entity": "", "lemma": "se", "pos_tag": "STOPWORD", "position": 8, "title": false}, "9": {"word": "met", "type_entity": "", "lemma": "mettre", "pos_tag": "VERB", "position": 9, "title": false}, "10": {"word": "progressivement", "type_entity": "", "lemma": "progressivement", "pos_tag": "ADV", "position": 10, "title": false}, "11": {"word": "en", "type_entity": "", "lemma": "en", "pos_tag": "STOPWORD", "position": 11, "title": false}, "12": {"word": "place", "type_entity": "", "lemma": "placer", "pos_tag": "NOUN", "position": 12, "title": false}, "13": {"word": "autour", "type_entity": "", "lemma": "autour", "pos_tag": "ADV", "position": 13, "title": true}, "14": {"word": "de", "type_entity": "", "lemma": "de", "pos_tag": "STOPWORD", "position": 14, "title": true}, "15": {"word": "la", "type_entity": "", "lemma": "le", "pos_tag": "STOPWORD", "position": 15, "title": true}, "16": {"word": "ZAD", "type_entity": "MISC", "lemma": "ZAD", "pos_tag": "PROPN", "position": 16, "title": true}, "17": {"word": "ce", "type_entity": "", "lemma": "ce", "pos_tag": "STOPWORD", "position": 17, "title": false}, "18": {"word": "mercredi", "type_entity": "", "lemma": "mercredi", "pos_tag": "NOUN", "position": 18, "title": false}, "19": {"word": "mercredi17janvieralors", "type_entity": "", "lemma": "mercredi17janvieralors", "pos_tag": "PROPN", "position": 19, "title": false}, "20": {"word": "que", "type_entity": "", "lemma": "que", "pos_tag": "STOPWORD", "position": 20, "title": false}, "21": {"word": "la", "type_entity": "", "lemma": "le", "pos_tag": "STOPWORD", "position": 21, "title": true}, "22": {"word": "decision", "type_entity": "", "lemma": "decision", "pos_tag": "NOUN", "position": 22, "title": false}, "23": {"word": "du", "type_entity": "", "lemma": "du", "pos_tag": "STOPWORD", "position": 23, "title": false}, "24": {"word": "gouvernement", "type_entity": "", "lemma": "gouvernement", "pos_tag": "NOUN", "position": 24, "title": false}, "25": {"word": "pourrait", "type_entity": "", "lemma": "pouvoir", "pos_tag": "STOPWORD", "position": 25, "title": false}, "26": {"word": "etre", "type_entity": "", "lemma": "etre", "pos_tag": "AUX", "position": 26, "title": false}, "27": {"word": "annoncee", "type_entity": "", "lemma": "annoncee", "pos_tag": "VERB", "position": 27, "title": false}, "28": {"word": "en", "type_entity": "", "lemma": "en", "pos_tag": "STOPWORD", "position": 28, "title": false}, "29": {"word": "fin", "type_entity": "", "lemma": "fin", "pos_tag": "NOUN", "position": 29, "title": false}, "30": {"word": "de", "type_entity": "", "lemma": "de", "pos_tag": "STOPWORD", "position": 30, "title": true}, "31": {"word": "matinee", "type_entity": "", "lemma": "matinee", "pos_tag": "NOUN", "position": 31, "title": false}, "32": {"word": ".", "type_entity": "", "lemma": ".", "pos_tag": "PUNCT", "position": 32, "title": false}, "33": {"word": "Survolee", "type_entity": "", "lemma": "Survolee", "pos_tag": "VERB", "position": 33, "title": false}, "34": {"word": "par", "type_entity": "", "lemma": "par", "pos_tag": "STOPWORD", "position": 34, "title": false}, "35": {"word": "des", "type_entity": "", "lemma": "un", "pos_tag": "STOPWORD", "position": 35, "title": false}, "36": {"word": "helicopteres", "type_entity": "", "lemma": "helicopteres", "pos_tag": "NOUN", "position": 36, "title": false}, "37": {"word": "de", "type_entity": "", "lemma": "de", "pos_tag": "STOPWORD", "position": 37, "title": true}, "38": {"word": "la", "type_entity": "", "lemma": "le", "pos_tag": "STOPWORD", "position": 38, "title": true}, "39": {"word": "gendarmerie", "type_entity": "", "lemma": "gendarmerie", "pos_tag": "NOUN", "position": 39, "title": false}, "40": {"word": "la", "type_entity": "", "lemma": "le", "pos_tag": "STOPWORD", "position": 40, "title": true}, "41": {"word": "zone", "type_entity": "", "lemma": "zone", "pos_tag": "NOUN", "position": 41, "title": false}, "42": {"word": "d", "type_entity": "", "lemma": "d", "pos_tag": "STOPWORD", "position": 42, "title": false}, "43": {"word": "amenagement", "type_entity": "", "lemma": "amenagement", "pos_tag": "ADV", "position": 43, "title": false}, "44": {"word": "differe", "type_entity": "", "lemma": "differe", "pos_tag": "VERB", "position": 44, "title": false}, "45": {"word": "est", "type_entity": "", "lemma": "être", "pos_tag": "STOPWORD", "position": 45, "title": false}, "46": {"word": "egalement", "type_entity": "", "lemma": "egalement", "pos_tag": "ADV", "position": 46, "title": false}, "47": {"word": "encerclee", "type_entity": "", "lemma": "encerclee", "pos_tag": "ADV", "position": 47, "title": false}, "48": {"word": "par", "type_entity": "", "lemma": "par", "pos_tag": "STOPWORD", "position": 48, "title": false}, "49": {"word": "sept", "type_entity": "", "lemma": "sept", "pos_tag": "STOPWORD", "position": 49, "title": false}, "50": {"word": "escadrons", "type_entity": "", "lemma": "escadron", "pos_tag": "NOUN", "position": 50, "title": false}, "51": {"word": "soit", "type_entity": "", "lemma": "être", "pos_tag": "STOPWORD", "position": 51, "title": false}, "52": {"word": "455", "type_entity": "", "lemma": "455", "pos_tag": "NUM", "position": 52, "title": false}, "53": {"word": "gendarmes", "type_entity": "", "lemma": "gendarme", "pos_tag": "NOUN", "position": 53, "title": true}, "54": {"word": "mobiles", "type_entity": "", "lemma": "mobile", "pos_tag": "ADJ", "position": 54, "title": false}, "55": {"word": "precise", "type_entity": "", "lemma": "precise", "pos_tag": "X", "position": 55, "title": false}, "56": {"word": "BFMTV", "type_entity": "", "lemma": "BFMTV", "pos_tag": "ADJ", "position": 56, "title": false}, "57": {"word": ".", "type_entity": "", "lemma": ".", "pos_tag": "PUNCT", "position": 57, "title": false}, "58": {"word": "Un", "type_entity": "", "lemma": "Un", "pos_tag": "DET", "position": 58, "title": false}, "59": {"word": "deploiement", "type_entity": "", "lemma": "deploiement", "pos_tag": "NOUN", "position": 59, "title": false}, "60": {"word": "qui", "type_entity": "", "lemma": "qui", "pos_tag": "STOPWORD", "position": 60, "title": false}, "61": {"word": "vise", "type_entity": "", "lemma": "viser", "pos_tag": "VERB", "position": 61, "title": false}, "62": {"word": "a", "type_entity": "", "lemma": "avoir", "pos_tag": "STOPWORD", "position": 62, "title": false}, "63": {"word": "controler", "type_entity": "", "lemma": "controler", "pos_tag": "VERB", "position": 63, "title": false}, "64": {"word": "et", "type_entity": "", "lemma": "et", "pos_tag": "STOPWORD", "position": 64, "title": false}, "65": {"word": "securiser", "type_entity": "", "lemma": "securiser", "pos_tag": "VERB", "position": 65, "title": false}, "66": {"word": "la", "type_entity": "", "lemma": "le", "pos_tag": "STOPWORD", "position": 66, "title": true}, "67": {"word": "zone", "type_entity": "", "lemma": "zone", "pos_tag": "NOUN", "position": 67, "title": false}, "68": {"word": "de", "type_entity": "", "lemma": "de", "pos_tag": "STOPWORD", "position": 68, "title": true}, "69": {"word": "1_600", "type_entity": "", "lemma": "1_600", "pos_tag": "NUM", "position": 69, "title": false}, "70": {"word": "hectares", "type_entity": "", "lemma": "hectare", "pos_tag": "NOUN", "position": 70, "title": false}, "71": {"word": "en", "type_entity": "", "lemma": "en", "pos_tag": "STOPWORD", "position": 71, "title": false}, "72": {"word": "prevision", "type_entity": "", "lemma": "prevision", "pos_tag": "NOUN", "position": 72, "title": false}, "73": {"word": "d", "type_entity": "", "lemma": "d", "pos_tag": "STOPWORD", "position": 73, "title": false}, "74": {"word": "une", "type_entity": "", "lemma": "un", "pos_tag": "STOPWORD", "position": 74, "title": false}, "75": {"word": "eventuelle", "type_entity": "", "lemma": "eventuelle", "pos_tag": "ADJ", "position": 75, "title": false}, "76": {"word": "evacuation", "type_entity": "", "lemma": "evacuation", "pos_tag": "NOUN", "position": 76, "title": false}, "77": {"word": ".", "type_entity": "", "lemma": ".", "pos_tag": "PUNCT", "position": 77, "title": false}, "78": {"word": "Selon", "type_entity": "", "lemma": "Selon", "pos_tag": "STOPWORD", "position": 78, "title": false}, "79": {"word": "l", "type_entity": "", "lemma": "l", "pos_tag": "STOPWORD", "position": 79, "title": false}, "80": {"word": "AFP", "type_entity": "ORG", "lemma": "AFP", "pos_tag": "PROPN", "position": 80, "title": false}, "81": {"word": "plusieurs", "type_entity": "", "lemma": "plusieurs", "pos_tag": "STOPWORD", "position": 81, "title": false}, "82": {"word": "compagnies", "type_entity": "", "lemma": "compagnie", "pos_tag": "NOUN", "position": 82, "title": false}, "83": {"word": "de", "type_entity": "", "lemma": "de", "pos_tag": "STOPWORD", "position": 83, "title": true}, "84": {"word": "CRS", "type_entity": "ORG", "lemma": "CRS", "pos_tag": "NOUN", "position": 84, "title": false}, "85": {"word": "sont", "type_entity": "", "lemma": "être", "pos_tag": "STOPWORD", "position": 85, "title": false}, "86": {"word": "egalement", "type_entity": "", "lemma": "egalement", "pos_tag": "ADV", "position": 86, "title": false}, "87": {"word": "en", "type_entity": "", "lemma": "en", "pos_tag": "STOPWORD", "position": 87, "title": false}, "88": {"word": "cours", "type_entity": "", "lemma": "courir", "pos_tag": "NOUN", "position": 88, "title": false}, "89": {"word": "de", "type_entity": "", "lemma": "de", "pos_tag": "STOPWORD", "position": 89, "title": true}, "90": {"word": "positionnement", "type_entity": "", "lemma": "positionnement", "pos_tag": "ADV", "position": 90, "title": false}, "91": {"word": "a", "type_entity": "", "lemma": "avoir", "pos_tag": "STOPWORD", "position": 91, "title": false}, "92": {"word": "Nantes", "type_entity": "LOC", "lemma": "Nantes", "pos_tag": "ADJ", "position": 92, "title": false}, "93": {"word": "et", "type_entity": "", "lemma": "et", "pos_tag": "STOPWORD", "position": 93, "title": false}, "94": {"word": "Rennes", "type_entity": "LOC", "lemma": "Rennes", "pos_tag": "PROPN", "position": 94, "title": false}, "95": {"word": "au", "type_entity": "", "lemma": "au", "pos_tag": "STOPWORD", "position": 95, "title": false}, "96": {"word": "cas", "type_entity": "", "lemma": "cas", "pos_tag": "NOUN", "position": 96, "title": false}, "97": {"word": "ou", "type_entity": "", "lemma": "ou", "pos_tag": "STOPWORD", "position": 97, "title": false}, "98": {"word": "des", "type_entity": "", "lemma": "un", "pos_tag": "STOPWORD", "position": 98, "title": false}, "99": {"word": "manifestations", "type_entity": "", "lemma": "manifestation", "pos_tag": "NOUN", "position": 99, "title": false}, "100": {"word": "seraient", "type_entity": "", "lemma": "être", "pos_tag": "STOPWORD", "position": 100, "title": false}, "101": {"word": "organisees", "type_entity": "", "lemma": "organisees", "pos_tag": "NOUN", "position": 101, "title": false}, "102": {"word": "a", "type_entity": "", "lemma": "avoir", "pos_tag": "STOPWORD", "position": 102, "title": false}, "103": {"word": "la", "type_entity": "", "lemma": "le", "pos_tag": "STOPWORD", "position": 103, "title": true}, "104": {"word": "suite", "type_entity": "", "lemma": "suite", "pos_tag": "NOUN", "position": 104, "title": false}, "105": {"word": "de", "type_entity": "", "lemma": "de", "pos_tag": "STOPWORD", "position": 105, "title": true}, "106": {"word": "la", "type_entity": "", "lemma": "le", "pos_tag": "STOPWORD", "position": 106, "title": true}, "107": {"word": "decision", "type_entity": "", "lemma": "decision", "pos_tag": "NOUN", "position": 107, "title": false}, "108": {"word": "du", "type_entity": "", "lemma": "du", "pos_tag": "STOPWORD", "position": 108, "title": false}, "109": {"word": "l", "type_entity": "", "lemma": "l", "pos_tag": "STOPWORD", "position": 109, "title": false}, "110": {"word": "executif", "type_entity": "", "lemma": "executif", "pos_tag": "NOUN", "position": 110, "title": false}, "111": {"word": ".", "type_entity": "", "lemma": ".", "pos_tag": "PUNCT", "position": 111, "title": false}, "112": {"word": "Car", "type_entity": "", "lemma": "Car", "pos_tag": "PRON", "position": 112, "title": false}, "113": {"word": "quelque", "type_entity": "", "lemma": "quelque", "pos_tag": "STOPWORD", "position": 113, "title": false}, "114": {"word": "soit", "type_entity": "", "lemma": "être", "pos_tag": "STOPWORD", "position": 114, "title": false}, "115": {"word": "la", "type_entity": "", "lemma": "le", "pos_tag": "STOPWORD", "position": 115, "title": true}, "116": {"word": "reponse", "type_entity": "", "lemma": "reponse", "pos_tag": "NOUN", "position": 116, "title": false}, "117": {"word": "du", "type_entity": "", "lemma": "du", "pos_tag": "STOPWORD", "position": 117, "title": false}, "118": {"word": "gouvernement", "type_entity": "", "lemma": "gouvernement", "pos_tag": "NOUN", "position": 118, "title": false}, "119": {"word": "celleci", "type_entity": "", "lemma": "celleci", "pos_tag": "PRON", "position": 119, "title": false}, "120": {"word": "sera", "type_entity": "", "lemma": "être", "pos_tag": "STOPWORD", "position": 120, "title": false}, "121": {"word": "mauvaise", "type_entity": "", "lemma": "mauvais", "pos_tag": "ADJ", "position": 121, "title": false}, "122": {"word": "pour", "type_entity": "", "lemma": "pour", "pos_tag": "STOPWORD", "position": 122, "title": false}, "123": {"word": "certains", "type_entity": "", "lemma": "certain", "pos_tag": "PRON", "position": 123, "title": false}, "124": {"word": "avait", "type_entity": "", "lemma": "avoir", "pos_tag": "STOPWORD", "position": 124, "title": false}, "125": {"word": "reconnu", "type_entity": "", "lemma": "reconnaître", "pos_tag": "VERB", "position": 125, "title": false}, "126": {"word": "des", "type_entity": "", "lemma": "un", "pos_tag": "STOPWORD", "position": 126, "title": false}, "127": {"word": "mardi", "type_entity": "", "lemma": "mardi", "pos_tag": "NOUN", "position": 127, "title": false}, "128": {"word": "le", "type_entity": "", "lemma": "le", "pos_tag": "STOPWORD", "position": 128, "title": false}, "129": {"word": "Premier", "type_entity": "", "lemma": "Premier", "pos_tag": "ADJ", "position": 129, "title": false}, "130": {"word": "ministre", "type_entity": "", "lemma": "ministre", "pos_tag": "NOUN", "position": 130, "title": false}, "131": {"word": "Edouard_Philippe", "type_entity": "PER", "lemma": "Edouard_Philippe", "pos_tag": "NOUN", "position": 131, "title": false}, "132": {"word": "devant", "type_entity": "", "lemma": "devoir", "pos_tag": "STOPWORD", "position": 132, "title": false}, "133": {"word": "les", "type_entity": "", "lemma": "le", "pos_tag": "STOPWORD", "position": 133, "title": false}, "134": {"word": "deputes", "type_entity": "", "lemma": "deputes", "pos_tag": "NOUN", "position": 134, "title": false}, "135": {"word": "LREM", "type_entity": "ORG", "lemma": "LREM", "pos_tag": "PROPN", "position": 135, "title": false}, "136": {"word": "en", "type_entity": "", "lemma": "en", "pos_tag": "STOPWORD", "position": 136, "title": false}, "137": {"word": "reunion", "type_entity": "", "lemma": "reunion", "pos_tag": "NOUN", "position": 137, "title": false}, "138": {"word": "de", "type_entity": "", "lemma": "de", "pos_tag": "STOPWORD", "position": 138, "title": true}, "139": {"word": "groupe", "type_entity": "", "lemma": "grouper", "pos_tag": "NOUN", "position": 139, "title": false}, "140": {"word": ".", "type_entity": "", "lemma": ".", "pos_tag": "PUNCT", "position": 140, "title": false}, "141": {"word": "La", "type_entity": "", "lemma": "La", "pos_tag": "STOPWORD", "position": 141, "title": true}, "142": {"word": "ZAD", "type_entity": "MISC", "lemma": "ZAD", "pos_tag": "PROPN", "position": 142, "title": true}, "143": {"word": "est", "type_entity": "", "lemma": "être", "pos_tag": "STOPWORD", "position": 143, "title": false}, "144": {"word": "actuellement", "type_entity": "", "lemma": "actuellement", "pos_tag": "ADV", "position": 144, "title": false}, "145": {"word": "occupee", "type_entity": "", "lemma": "occupee", "pos_tag": "VERB", "position": 145, "title": false}, "146": {"word": "par", "type_entity": "", "lemma": "par", "pos_tag": "STOPWORD", "position": 146, "title": false}, "147": {"word": "150", "type_entity": "", "lemma": "150", "pos_tag": "PRON", "position": 147, "title": false}, "148": {"word": "a", "type_entity": "", "lemma": "avoir", "pos_tag": "STOPWORD", "position": 148, "title": false}, "149": {"word": "2_0", "type_entity": "", "lemma": "2_0", "pos_tag": "NUM", "position": 149, "title": false}, "150": {"word": "personnes", "type_entity": "", "lemma": "personne", "pos_tag": "NOUN", "position": 150, "title": false}, "151": {"word": "qui", "type_entity": "", "lemma": "qui", "pos_tag": "STOPWORD", "position": 151, "title": false}, "152": {"word": "selon", "type_entity": "", "lemma": "selon", "pos_tag": "STOPWORD", "position": 152, "title": false}, "153": {"word": "les", "type_entity": "", "lemma": "le", "pos_tag": "STOPWORD", "position": 153, "title": false}, "154": {"word": "autorites", "type_entity": "", "lemma": "autorites", "pos_tag": "NOUN", "position": 154, "title": false}, "155": {"word": "en", "type_entity": "", "lemma": "en", "pos_tag": "STOPWORD", "position": 155, "title": false}, "156": {"word": "ont", "type_entity": "", "lemma": "avoir", "pos_tag": "STOPWORD", "position": 156, "title": false}, "157": {"word": "fait", "type_entity": "", "lemma": "faire", "pos_tag": "STOPWORD", "position": 157, "title": false}, "158": {"word": "un", "type_entity": "", "lemma": "un", "pos_tag": "STOPWORD", "position": 158, "title": false}, "159": {"word": "camp", "type_entity": "", "lemma": "camp", "pos_tag": "NOUN", "position": 159, "title": false}, "160": {"word": "retranche", "type_entity": "", "lemma": "retrancher", "pos_tag": "NOUN", "position": 160, "title": false}, "161": {"word": ".", "type_entity": "", "lemma": ".", "pos_tag": "PUNCT", "position": 161, "title": false}, "162": {"word": "La", "type_entity": "", "lemma": "La", "pos_tag": "STOPWORD", "position": 162, "title": true}, "163": {"word": "zone", "type_entity": "", "lemma": "zone", "pos_tag": "NOUN", "position": 163, "title": false}, "164": {"word": "sera", "type_entity": "", "lemma": "être", "pos_tag": "STOPWORD", "position": 164, "title": false}, "165": {"word": "evacuee", "type_entity": "", "lemma": "evacuee", "pos_tag": "NOUN", "position": 165, "title": false}, "166": {"word": "des", "type_entity": "", "lemma": "un", "pos_tag": "STOPWORD", "position": 166, "title": false}, "167": {"word": "elements", "type_entity": "", "lemma": "elements", "pos_tag": "NOUN", "position": 167, "title": false}, "168": {"word": "les", "type_entity": "", "lemma": "le", "pos_tag": "STOPWORD", "position": 168, "title": false}, "169": {"word": "plus", "type_entity": "", "lemma": "plaire", "pos_tag": "STOPWORD", "position": 169, "title": true}, "170": {"word": "radicaux", "type_entity": "", "lemma": "radical", "pos_tag": "NOUN", "position": 170, "title": false}, "171": {"word": "a", "type_entity": "", "lemma": "avoir", "pos_tag": "STOPWORD", "position": 171, "title": false}, "172": {"word": "affirme", "type_entity": "", "lemma": "affirmer", "pos_tag": "VERB", "position": 172, "title": false}, "173": {"word": "mardi", "type_entity": "", "lemma": "mardi", "pos_tag": "NOUN", "position": 173, "title": false}, "174": {"word": "le", "type_entity": "", "lemma": "le", "pos_tag": "STOPWORD", "position": 174, "title": false}, "175": {"word": "ministre", "type_entity": "", "lemma": "ministre", "pos_tag": "NOUN", "position": 175, "title": false}, "176": {"word": "de", "type_entity": "", "lemma": "de", "pos_tag": "STOPWORD", "position": 176, "title": true}, "177": {"word": "l", "type_entity": "", "lemma": "l", "pos_tag": "STOPWORD", "position": 177, "title": false}, "178": {"word": "Interieur_Gerard_Collomb", "type_entity": "PER", "lemma": "Interieur_Gerard_Collomb", "pos_tag": "ADJ", "position": 178, "title": false}, "179": {"word": "sur", "type_entity": "", "lemma": "sur", "pos_tag": "STOPWORD", "position": 179, "title": false}, "180": {"word": "France", "type_entity": "LOC", "lemma": "France", "pos_tag": "PROPN", "position": 180, "title": false}, "181": {"word": "2", "type_entity": "", "lemma": "2", "pos_tag": "NUM", "position": 181, "title": false}, "182": {"word": ".", "type_entity": "", "lemma": ".", "pos_tag": "PUNCT", "position": 182, "title": false}, "183": {"word": "Qu", "type_entity": "", "lemma": "Qu", "pos_tag": "DET", "position": 183, "title": false}, "184": {"word": "ils", "type_entity": "", "lemma": "il", "pos_tag": "STOPWORD", "position": 184, "title": false}, "185": {"word": "soient", "type_entity": "", "lemma": "être", "pos_tag": "STOPWORD", "position": 185, "title": false}, "186": {"word": "pour", "type_entity": "", "lemma": "pour", "pos_tag": "STOPWORD", "position": 186, "title": false}, "187": {"word": "ou", "type_entity": "", "lemma": "ou", "pos_tag": "STOPWORD", "position": 187, "title": false}, "188": {"word": "contre", "type_entity": "", "lemma": "contrer", "pos_tag": "STOPWORD", "position": 188, "title": false}, "189": {"word": "l", "type_entity": "", "lemma": "l", "pos_tag": "STOPWORD", "position": 189, "title": false}, "190": {"word": "aeroport", "type_entity": "", "lemma": "aeroport", "pos_tag": "VERB", "position": 190, "title": false}, "191": {"word": "la", "type_entity": "", "lemma": "le", "pos_tag": "STOPWORD", "position": 191, "title": true}, "192": {"word": "quasitotalite", "type_entity": "", "lemma": "quasitotalite", "pos_tag": "NOUN", "position": 192, "title": false}, "193": {"word": "des", "type_entity": "", "lemma": "un", "pos_tag": "STOPWORD", "position": 193, "title": false}, "194": {"word": "elus", "type_entity": "", "lemma": "elus", "pos_tag": "NOUN", "position": 194, "title": false}, "195": {"word": "locaux", "type_entity": "", "lemma": "local", "pos_tag": "ADJ", "position": 195, "title": false}, "196": {"word": "defendent", "type_entity": "", "lemma": "defendent", "pos_tag": "ADV", "position": 196, "title": false}, "197": {"word": "son", "type_entity": "", "lemma": "son", "pos_tag": "STOPWORD", "position": 197, "title": false}, "198": {"word": "evacuation", "type_entity": "", "lemma": "evacuation", "pos_tag": "NOUN", "position": 198, "title": false}, "199": {"word": "six", "type_entity": "", "lemma": "six", "pos_tag": "STOPWORD", "position": 199, "title": false}, "200": {"word": "ans", "type_entity": "", "lemma": "an", "pos_tag": "NOUN", "position": 200, "title": false}, "201": {"word": "apres", "type_entity": "", "lemma": "apres", "pos_tag": "ADJ", "position": 201, "title": false}, "202": {"word": "le", "type_entity": "", "lemma": "le", "pos_tag": "STOPWORD", "position": 202, "title": false}, "203": {"word": "fiasco", "type_entity": "", "lemma": "fiasco", "pos_tag": "NOUN", "position": 203, "title": false}, "204": {"word": "d", "type_entity": "", "lemma": "d", "pos_tag": "STOPWORD", "position": 204, "title": false}, "205": {"word": "une", "type_entity": "", "lemma": "un", "pos_tag": "STOPWORD", "position": 205, "title": false}, "206": {"word": "premiere", "type_entity": "", "lemma": "premiere", "pos_tag": "ADJ", "position": 206, "title": false}, "207": {"word": "tentative", "type_entity": "", "lemma": "tentative", "pos_tag": "NOUN", "position": 207, "title": false}, "208": {"word": "en", "type_entity": "", "lemma": "en", "pos_tag": "STOPWORD", "position": 208, "title": false}, "209": {"word": "octobre2012", "type_entity": "LOC", "lemma": "octobre2012", "pos_tag": "NOUN", "position": 209, "title": false}, "210": {"word": ".", "type_entity": "", "lemma": ".", "pos_tag": "PUNCT", "position": 210, "title": false}, "211": {"word": "Mais", "type_entity": "", "lemma": "Mais", "pos_tag": "STOPWORD", "position": 211, "title": false}, "212": {"word": "une", "type_entity": "", "lemma": "un", "pos_tag": "STOPWORD", "position": 212, "title": false}, "213": {"word": "evacuation", "type_entity": "", "lemma": "evacuation", "pos_tag": "NOUN", "position": 213, "title": false}, "214": {"word": "qui", "type_entity": "", "lemma": "qui", "pos_tag": "STOPWORD", "position": 214, "title": false}, "215": {"word": "mobiliserait", "type_entity": "", "lemma": "mobiliser", "pos_tag": "VERB", "position": 215, "title": false}, "216": {"word": "au", "type_entity": "", "lemma": "au", "pos_tag": "STOPWORD", "position": 216, "title": false}, "217": {"word": "minimum", "type_entity": "", "lemma": "minimum", "pos_tag": "VERB", "position": 217, "title": false}, "218": {"word": "2_000", "type_entity": "", "lemma": "2_000", "pos_tag": "NUM", "position": 218, "title": false}, "219": {"word": "gendarmes", "type_entity": "", "lemma": "gendarme", "pos_tag": "NOUN", "position": 219, "title": true}, "220": {"word": "mobiles", "type_entity": "", "lemma": "mobile", "pos_tag": "ADJ", "position": 220, "title": false}, "221": {"word": "s", "type_entity": "", "lemma": "avoir", "pos_tag": "STOPWORD", "position": 221, "title": false}, "222": {"word": "annonce", "type_entity": "", "lemma": "annoncer", "pos_tag": "VERB", "position": 222, "title": false}, "223": {"word": "beaucoup", "type_entity": "", "lemma": "beaucoup", "pos_tag": "STOPWORD", "position": 223, "title": false}, "224": {"word": "plus", "type_entity": "", "lemma": "plaire", "pos_tag": "STOPWORD", "position": 224, "title": true}, "225": {"word": "aisee", "type_entity": "", "lemma": "aisee", "pos_tag": "VERB", "position": 225, "title": false}, "226": {"word": "si", "type_entity": "", "lemma": "si", "pos_tag": "STOPWORD", "position": 226, "title": false}, "227": {"word": "le", "type_entity": "", "lemma": "le", "pos_tag": "STOPWORD", "position": 227, "title": false}, "228": {"word": "projet", "type_entity": "", "lemma": "projet", "pos_tag": "NOUN", "position": 228, "title": false}, "229": {"word": "d", "type_entity": "", "lemma": "d", "pos_tag": "STOPWORD", "position": 229, "title": false}, "230": {"word": "aeroport", "type_entity": "", "lemma": "aeroport", "pos_tag": "NOUN", "position": 230, "title": false}, "231": {"word": "est", "type_entity": "", "lemma": "être", "pos_tag": "STOPWORD", "position": 231, "title": false}, "232": {"word": "abandonne", "type_entity": "", "lemma": "abandonner", "pos_tag": "VERB", "position": 232, "title": false}, "233": {"word": ".", "type_entity": "", "lemma": ".", "pos_tag": "PUNCT", "position": 233, "title": false}, "234": {"word": "Soutenues", "type_entity": "LOC", "lemma": "Soutenues", "pos_tag": "VERB", "position": 234, "title": false}, "235": {"word": "par", "type_entity": "", "lemma": "par", "pos_tag": "STOPWORD", "position": 235, "title": false}, "236": {"word": "des", "type_entity": "", "lemma": "un", "pos_tag": "STOPWORD", "position": 236, "title": false}, "237": {"word": "ONG", "type_entity": "", "lemma": "ONG", "pos_tag": "NOUN", "position": 237, "title": false}, "238": {"word": "comme", "type_entity": "", "lemma": "comme", "pos_tag": "STOPWORD", "position": 238, "title": false}, "239": {"word": "Greenpeace", "type_entity": "ORG", "lemma": "Greenpeace", "pos_tag": "NOUN", "position": 239, "title": false}, "240": {"word": "une", "type_entity": "", "lemma": "un", "pos_tag": "STOPWORD", "position": 240, "title": false}, "241": {"word": "poignee", "type_entity": "", "lemma": "poignee", "pos_tag": "NOUN", "position": 241, "title": false}, "242": {"word": "de", "type_entity": "", "lemma": "de", "pos_tag": "STOPWORD", "position": 242, "title": true}, "243": {"word": "personnes", "type_entity": "", "lemma": "personne", "pos_tag": "NOUN", "position": 243, "title": false}, "244": {"word": "comme", "type_entity": "", "lemma": "comme", "pos_tag": "STOPWORD", "position": 244, "title": false}, "245": {"word": "l", "type_entity": "", "lemma": "l", "pos_tag": "STOPWORD", "position": 245, "title": false}, "246": {"word": "eurodepute", "type_entity": "", "lemma": "eurodepute", "pos_tag": "ADJ", "position": 246, "title": false}, "247": {"word": "Jose_Bove", "type_entity": "PER", "lemma": "Jose_Bove", "pos_tag": "PROPN", "position": 247, "title": false}, "248": {"word": "ou", "type_entity": "", "lemma": "ou", "pos_tag": "STOPWORD", "position": 248, "title": false}, "249": {"word": "le", "type_entity": "", "lemma": "le", "pos_tag": "STOPWORD", "position": 249, "title": false}, "250": {"word": "depute", "type_entity": "", "lemma": "depute", "pos_tag": "NOUN", "position": 250, "title": false}, "251": {"word": "LREM", "type_entity": "ORG", "lemma": "LREM", "pos_tag": "PROPN", "position": 251, "title": false}, "252": {"word": "Matthieu_Orphelin", "type_entity": "MISC", "lemma": "Matthieu_Orphelin", "pos_tag": "ADJ", "position": 252, "title": false}, "253": {"word": ",", "type_entity": "", "lemma": ",", "pos_tag": "PUNCT", "position": 253, "title": false}, "254": {"word": "plaident", "type_entity": "", "lemma": "plaider", "pos_tag": "NOUN", "position": 254, "title": false}, "255": {"word": "pour", "type_entity": "", "lemma": "pour", "pos_tag": "STOPWORD", "position": 255, "title": false}, "256": {"word": "renoncer", "type_entity": "", "lemma": "renoncer", "pos_tag": "NOUN", "position": 256, "title": false}, "257": {"word": "a", "type_entity": "", "lemma": "avoir", "pos_tag": "STOPWORD", "position": 257, "title": false}, "258": {"word": "une", "type_entity": "", "lemma": "un", "pos_tag": "STOPWORD", "position": 258, "title": false}, "259": {"word": "\"", "type_entity": "", "lemma": "\"", "pos_tag": "PUNCT", "position": 259, "title": false}, "260": {"word": "evacuation", "type_entity": "", "lemma": "evacuation", "pos_tag": "NOUN", "position": 260, "title": false}, "261": {"word": "violente", "type_entity": "", "lemma": "violenter", "pos_tag": "ADJ", "position": 261, "title": false}, "262": {"word": "\"", "type_entity": "", "lemma": "\"", "pos_tag": "PUNCT", "position": 262, "title": false}, "263": {"word": "et", "type_entity": "", "lemma": "et", "pos_tag": "STOPWORD", "position": 263, "title": false}, "264": {"word": "preconisent", "type_entity": "", "lemma": "preconisent", "pos_tag": "NOUN", "position": 264, "title": false}, "265": {"word": "d", "type_entity": "", "lemma": "d", "pos_tag": "STOPWORD", "position": 265, "title": false}, "266": {"word": "aller", "type_entity": "", "lemma": "aller", "pos_tag": "VERB", "position": 266, "title": false}, "267": {"word": "vers", "type_entity": "", "lemma": "ver", "pos_tag": "STOPWORD", "position": 267, "title": false}, "268": {"word": "un", "type_entity": "", "lemma": "un", "pos_tag": "STOPWORD", "position": 268, "title": false}, "269": {"word": "\"", "type_entity": "", "lemma": "\"", "pos_tag": "PUNCT", "position": 269, "title": false}, "270": {"word": "nouvel", "type_entity": "", "lemma": "nouveau", "pos_tag": "ADJ", "position": 270, "title": false}, "271": {"word": "avenir", "type_entity": "", "lemma": "avenir", "pos_tag": "NOUN", "position": 271, "title": false}, "272": {"word": "\"", "type_entity": "", "lemma": "\"", "pos_tag": "PUNCT", "position": 272, "title": false}, "273": {"word": "similaire", "type_entity": "", "lemma": "similaire", "pos_tag": "ADJ", "position": 273, "title": false}, "274": {"word": "a", "type_entity": "", "lemma": "avoir", "pos_tag": "STOPWORD", "position": 274, "title": false}, "275": {"word": "l", "type_entity": "", "lemma": "l", "pos_tag": "STOPWORD", "position": 275, "title": false}, "276": {"word": "experience", "type_entity": "", "lemma": "experience", "pos_tag": "NOUN", "position": 276, "title": false}, "277": {"word": "du", "type_entity": "", "lemma": "du", "pos_tag": "STOPWORD", "position": 277, "title": false}, "278": {"word": "Larzac", "type_entity": "LOC", "lemma": "Larzac", "pos_tag": "PROPN", "position": 278, "title": false}, "279": {"word": "dans", "type_entity": "", "lemma": "dan", "pos_tag": "STOPWORD", "position": 279, "title": false}, "280": {"word": "les", "type_entity": "", "lemma": "le", "pos_tag": "STOPWORD", "position": 280, "title": false}, "281": {"word": "annees", "type_entity": "", "lemma": "annees", "pos_tag": "NOUN", "position": 281, "title": false}, "282": {"word": "70", "type_entity": "", "lemma": "70", "pos_tag": "PRON", "position": 282, "title": false}, "283": {"word": ".", "type_entity": "", "lemma": ".", "pos_tag": "PUNCT", "position": 283, "title": false}, "284": {"word": "M.C.", "type_entity": "", "lemma": "M.C.", "pos_tag": "PUNCT", "position": 284, "title": false}, "285": {"word": "Avec", "type_entity": "", "lemma": "Avec", "pos_tag": "ADP", "position": 285, "title": false}, "286": {"word": "AFP", "type_entity": "ORG", "lemma": "AFP", "pos_tag": "PROPN", "position": 286, "title": false}, "287": {"word": "L", "type_entity": "", "lemma": "L", "pos_tag": "STOPWORD", "position": 287, "title": false}, "288": {"word": "Obs", "type_entity": "", "lemma": "Obs", "pos_tag": "PROPN", "position": 288, "title": false}, "words": ["Journee_cruciale", "a", "NotreDamedesLandes", ".", "Le", "dispositif", "policier", "se", "met", "progressivement", "en", "place", "autour", "de", "la", "ZAD", "ce", "mercredi", "mercredi17janvieralors", "que", "la", "decision", "du", "gouvernement", "pourrait", "etre", "annoncee", "en", "fin", "de", "matinee", ".", "Survolee", "par", "des", "helicopteres", "de", "la", "gendarmerie", "la", "zone", "d", "amenagement", "differe", "est", "egalement", "encerclee", "par", "sept", "escadrons", "soit", "455", "gendarmes", "mobiles", "precise", "BFMTV", ".", "Un", "deploiement", "qui", "vise", "a", "controler", "et", "securiser", "la", "zone", "de", "1_600", "hectares", "en", "prevision", "d", "une", "eventuelle", "evacuation", ".", "Selon", "l", "AFP", "plusieurs", "compagnies", "de", "CRS", "sont", "egalement", "en", "cours", "de", "positionnement", "a", "Nantes", "et", "Rennes", "au", "cas", "ou", "des", "manifestations", "seraient", "organisees", "a", "la", "suite", "de", "la", "decision", "du", "l", "executif", ".", "Car", "quelque", "soit", "la", "reponse", "du", "gouvernement", "celleci", "sera", "mauvaise", "pour", "certains", "avait", "reconnu", "des", "mardi", "le", "Premier", "ministre", "Edouard_Philippe", "devant", "les", "deputes", "LREM", "en", "reunion", "de", "groupe", ".", "La", "ZAD", "est", "actuellement", "occupee", "par", "150", "a", "2_0", "personnes", "qui", "selon", "les", "autorites", "en", "ont", "fait", "un", "camp", "retranche", ".", "La", "zone", "sera", "evacuee", "des", "elements", "les", "plus", "radicaux", "a", "affirme", "mardi", "le", "ministre", "de", "l", "Interieur_Gerard_Collomb", "sur", "France", "2", ".", "Qu", "ils", "soient", "pour", "ou", "contre", "l", "aeroport", "la", "quasitotalite", "des", "elus", "locaux", "defendent", "son", "evacuation", "six", "ans", "apres", "le", "fiasco", "d", "une", "premiere", "tentative", "en", "octobre2012", ".", "Mais", "une", "evacuation", "qui", "mobiliserait", "au", "minimum", "2_000", "gendarmes", "mobiles", "s", "annonce", "beaucoup", "plus", "aisee", "si", "le", "projet", "d", "aeroport", "est", "abandonne", ".", "Soutenues", "par", "des", "ONG", "comme", "Greenpeace", "une", "poignee", "de", "personnes", "comme", "l", "eurodepute", "Jose_Bove", "ou", "le", "depute", "LREM", "Matthieu_Orphelin", ",", "plaident", "pour", "renoncer", "a", "une", "\"", "evacuation", "violente", "\"", "et", "preconisent", "d", "aller", "vers", "un", "\"", "nouvel", "avenir", "\"", "similaire", "a", "l", "experience", "du", "Larzac", "dans", "les", "annees", "70", ".", "M.C.", "Avec", "AFP", "L", "Obs"], "list_lemma": ["Journee_cruciale", "avoir", "NotreDamedesLandes", ".", "Le", "dispositif", "policier", "se", "mettre", "progressivement", "en", "placer", "autour", "de", "le", "ZAD", "ce", "mercredi", "mercredi17janvieralors", "que", "le", "decision", "du", "gouvernement", "pouvoir", "etre", "annoncee", "en", "fin", "de", "matinee", ".", "Survolee", "par", "un", "helicopteres", "de", "le", "gendarmerie", "le", "zone", "d", "amenagement", "differe", "être", "egalement", "encerclee", "par", "sept", "escadron", "être", "455", "gendarme", "mobile", "precise", "BFMTV", ".", "Un", "deploiement", "qui", "viser", "avoir", "controler", "et", "securiser", "le", "zone", "de", "1_600", "hectare", "en", "prevision", "d", "un", "eventuelle", "evacuation", ".", "Selon", "l", "AFP", "plusieurs", "compagnie", "de", "CRS", "être", "egalement", "en", "courir", "de", "positionnement", "avoir", "Nantes", "et", "Rennes", "au", "cas", "ou", "un", "manifestation", "être", "organisees", "avoir", "le", "suite", "de", "le", "decision", "du", "l", "executif", ".", "Car", "quelque", "être", "le", "reponse", "du", "gouvernement", "celleci", "être", "mauvais", "pour", "certain", "avoir", "reconnaître", "un", "mardi", "le", "Premier", "ministre", "Edouard_Philippe", "devoir", "le", "deputes", "LREM", "en", "reunion", "de", "grouper", ".", "La", "ZAD", "être", "actuellement", "occupee", "par", "150", "avoir", "2_0", "personne", "qui", "selon", "le", "autorites", "en", "avoir", "faire", "un", "camp", "retrancher", ".", "La", "zone", "être", "evacuee", "un", "elements", "le", "plaire", "radical", "avoir", "affirmer", "mardi", "le", "ministre", "de", "l", "Interieur_Gerard_Collomb", "sur", "France", "2", ".", "Qu", "il", "être", "pour", "ou", "contrer", "l", "aeroport", "le", "quasitotalite", "un", "elus", "local", "defendent", "son", "evacuation", "six", "an", "apres", "le", "fiasco", "d", "un", "premiere", "tentative", "en", "octobre2012", ".", "Mais", "un", "evacuation", "qui", "mobiliser", "au", "minimum", "2_000", "gendarme", "mobile", "avoir", "annoncer", "beaucoup", "plaire", "aisee", "si", "le", "projet", "d", "aeroport", "être", "abandonner", ".", "Soutenues", "par", "un", "ONG", "comme", "Greenpeace", "un", "poignee", "de", "personne", "comme", "l", "eurodepute", "Jose_Bove", "ou", "le", "depute", "LREM", "Matthieu_Orphelin", ",", "plaider", "pour", "renoncer", "avoir", "un", "\"", "evacuation", "violenter", "\"", "et", "preconisent", "d", "aller", "ver", "un", "\"", "nouveau", "avenir", "\"", "similaire", "avoir", "l", "experience", "du", "Larzac", "dan", "le", "annees", "70", ".", "M.C.", "Avec", "AFP", "L", "Obs"]}, "author": ["L'Obs"], "newspaper": "NouvelObservateur"}